{"a196748":{"bookmarkId":"196748","name":"SirRajTheElf","isFavorite":"1","isFriendly":"0","isHostile":"0","tileId":"414771","xCoord":"480","yCoord":"531","tileLevel":"9","tileCityId":"117786","tileUserId":"225831","displayName":"SirRajTheElf","race":"2","cityId":"117786","cityUserId":"225831","cityName":"NewCity4U93"},"a198480":{"bookmarkId":"198480","name":"Slifier","isFavorite":"1","isFriendly":"0","isHostile":"0","tileId":"285700","xCoord":"625","yCoord":"300","tileLevel":"6","tileCityId":"117489","tileUserId":"1012055","displayName":"Slifiier","race":"2","cityId":"117489","cityUserId":"1012055","cityName":"Slifier"},"a200089":{"bookmarkId":"200089","name":"Farm 044 351 good","isFavorite":"0","isFriendly":"1","isHostile":"0","tileId":"170866","xCoord":"44","yCoord":"351","tileLevel":"6","tileCityId":"44721","tileUserId":"95852","displayName":"Ax3l","race":"1","cityId":"44721","cityUserId":"95852","cityName":"Radon"},"a200116":{"bookmarkId":"200116","name":"Nicole","isFavorite":"1","isFriendly":"0","isHostile":"0","tileId":"325538","xCoord":"38","yCoord":"468","tileLevel":"8","tileCityId":"122906","tileUserId":"566620","displayName":"XXNICOLEXX","race":"1","cityId":"122906","cityUserId":"566620","cityName":"NewCityC57G"},"a200152":{"bookmarkId":"200152","name":"Farm 018 005","isFavorite":"0","isFriendly":"0","isHostile":"0","tileId":"315","xCoord":"18","yCoord":"5","tileLevel":"4","tileCityId":"88797","tileUserId":"226772","displayName":"edstark","race":"2","cityId":"88797","cityUserId":"226772","cityName":"NewCity4UZ8"},"a200377":{"bookmarkId":"200377","name":"Farm 031 013","isFavorite":"0","isFriendly":"0","isHostile":"0","tileId":"4253","xCoord":"31","yCoord":"13","tileLevel":"5","tileCityId":"26286","tileUserId":"42792","displayName":"Declan21","race":"2","cityId":"26286","cityUserId":"42792","cityName":"Kaladrium II"},"a200397":{"bookmarkId":"200397","name":"Ninja kingdom","isFavorite":"1","isFriendly":"0","isHostile":"0","tileId":"622746","xCoord":"720","yCoord":"726","tileLevel":"3","tileCityId":"127404","tileUserId":"1880623","displayName":"ElvenNinja","race":"2","cityId":"127404","cityUserId":"1880623","cityName":"Ninja kingdom"},"a200928":{"bookmarkId":"200928","name":"Farm 123 150 good","isFavorite":"0","isFriendly":"1","isHostile":"0","tileId":"26840","xCoord":"123","yCoord":"150","tileLevel":"8","tileCityId":"63886","tileUserId":"151360","displayName":"Ave","race":"2","cityId":"63886","cityUserId":"151360","cityName":"Hope for all"},"a201152":{"bookmarkId":"201152","name":"Blobb","isFavorite":"1","isFriendly":"0","isHostile":"0","tileId":"73845","xCoord":"374","yCoord":"90","tileLevel":"9","tileCityId":"120209","tileUserId":"706873","displayName":"BlobbBlobb","race":"2","cityId":"120209","cityUserId":"706873","cityName":"Hell"},"a201827":{"bookmarkId":"201827","name":"Farm 006 037 big","isFavorite":"0","isFriendly":"1","isHostile":"0","tileId":"577","xCoord":"6","yCoord":"37","tileLevel":"9","tileCityId":"69814","tileUserId":"167159","displayName":"Kiwimate","race":"2","cityId":"69814","cityUserId":"167159","cityName":"Waitakere"},"a202623":{"bookmarkId":"202623","name":"Farm 001 035","isFavorite":"0","isFriendly":"0","isHostile":"0","tileId":"455","xCoord":"1","yCoord":"35","tileLevel":"4","tileCityId":"85590","tileUserId":"218048","displayName":"Calamity","race":"2","cityId":"85590","cityUserId":"218048","cityName":"NewCity4O8W"},"a203604":{"bookmarkId":"203604","name":"Alternate","isFavorite":"0","isFriendly":"1","isHostile":"0","tileId":"298540","xCoord":"688","yCoord":"330","tileLevel":"5","tileCityId":"110934","tileUserId":"576386","displayName":"Alternate","race":"2","cityId":"110934","cityUserId":"576386","cityName":"Here we go"},"a203901":{"bookmarkId":"203901","name":"Farm 022 086","isFavorite":"0","isFriendly":"0","isHostile":"0","tileId":"5631","xCoord":"22","yCoord":"86","tileLevel":"5","tileCityId":"11678","tileUserId":"17360","displayName":"james_c","race":"2","cityId":"11678","cityUserId":"17360","cityName":"NewCityDE8"},"a203952":{"bookmarkId":"203952","name":"Farm 024 055","isFavorite":"0","isFriendly":"0","isHostile":"0","tileId":"4870","xCoord":"24","yCoord":"55","tileLevel":"3","tileCityId":"115804","tileUserId":"1005536","displayName":"Turon","race":"2","cityId":"115804","cityUserId":"1005536","cityName":"Nargothrond"},"a210978":{"bookmarkId":"210978","name":"Farm 120 146 good","isFavorite":"0","isFriendly":"1","isHostile":"0","tileId":"23146","xCoord":"120","yCoord":"146","tileLevel":"5","tileCityId":"123544","tileUserId":"491356","displayName":"Might_o","race":"2","cityId":"123544","cityUserId":"491356","cityName":"stop_please"},"a210985":{"bookmarkId":"210985","name":"Farm 122 135","isFavorite":"0","isFriendly":"0","isHostile":"0","tileId":"26460","xCoord":"122","yCoord":"135","tileLevel":"5","tileCityId":"21106","tileUserId":"30008","displayName":"moria1","race":"1","cityId":"21106","cityUserId":"30008","cityName":"NewCityN5K"},"a211011":{"bookmarkId":"211011","name":"Farm 109 112","isFavorite":"0","isFriendly":"0","isHostile":"0","tileId":"22167","xCoord":"109","yCoord":"112","tileLevel":"4","tileCityId":"114271","tileUserId":"798616","displayName":"Zenoa","race":"2","cityId":"114271","cityUserId":"798616","cityName":"Rowanoak"},"a211093":{"bookmarkId":"211093","name":"Farm 130 119 good","isFavorite":"0","isFriendly":"1","isHostile":"0","tileId":"26199","xCoord":"130","yCoord":"119","tileLevel":"6","tileCityId":"94953","tileUserId":"246056","displayName":"jimbo4321","race":"2","cityId":"94953","cityUserId":"246056","cityName":"Jimboleen"},"a211117":{"bookmarkId":"211117","name":"Farm 132 076","isFavorite":"0","isFriendly":"0","isHostile":"0","tileId":"25481","xCoord":"132","yCoord":"76","tileLevel":"5","tileCityId":"64742","tileUserId":"153808","displayName":"Skybond","race":"1","cityId":"64742","cityUserId":"153808","cityName":"NewCity3AOG"},"a212589":{"bookmarkId":"212589","name":"Farm 099 133 food","isFavorite":"0","isFriendly":"1","isHostile":"0","tileId":"18768","xCoord":"99","yCoord":"133","tileLevel":"4","tileCityId":"43672","tileUserId":"93024","displayName":"Brian25","race":"2","cityId":"43672","cityUserId":"93024","cityName":"Willville"},"a213765":{"bookmarkId":"213765","name":"Farm 110 140 good","isFavorite":"0","isFriendly":"1","isHostile":"0","tileId":"22600","xCoord":"110","yCoord":"140","tileLevel":"6","tileCityId":"88447","tileUserId":"225728","displayName":"childermass","race":"1","cityId":"88447","cityUserId":"225728","cityName":"mattistan"},"a221693":{"bookmarkId":"221693","name":"Toprak","isFavorite":"1","isFriendly":"0","isHostile":"0","tileId":"451539","xCoord":"658","yCoord":"569","tileLevel":"9","tileCityId":"129992","tileUserId":"1915202","displayName":"Toprak","race":"1","cityId":"129992","cityUserId":"1915202","cityName":"Cagri1986"},"a225945":{"bookmarkId":"225945","name":"Wilhelm's Land","isFavorite":"1","isFriendly":"0","isHostile":"0","tileId":"120533","xCoord":"607","yCoord":"28","tileLevel":"9","tileCityId":"48490","tileUserId":"106133","displayName":"Wilhelmjohann","race":"2","cityId":"48490","cityUserId":"106133","cityName":"Wilhelm's Land"},"a226873":{"bookmarkId":"226873","name":"Farm 026 033 good","isFavorite":"0","isFriendly":"1","isHostile":"0","tileId":"4553","xCoord":"26","yCoord":"33","tileLevel":"5","tileCityId":"87119","tileUserId":"221928","displayName":"Grimble","race":"2","cityId":"87119","cityUserId":"221928","cityName":"Torentas"},"a228699":{"bookmarkId":"228699","name":"Farm 135 004 good","isFavorite":"0","isFriendly":"1","isHostile":"0","tileId":"24224","xCoord":"135","yCoord":"4","tileLevel":"8","tileCityId":"27733","tileUserId":"47329","displayName":"Xandros","race":"2","cityId":"27733","cityUserId":"47329","cityName":"Algren"},"a229591":{"bookmarkId":"229591","name":"Farm 113 036 good","isFavorite":"0","isFriendly":"1","isHostile":"0","tileId":"20686","xCoord":"113","yCoord":"36","tileLevel":"4","tileCityId":"36724","tileUserId":"72496","displayName":"Uludil","race":"2","cityId":"36724","cityUserId":"72496","cityName":"Uluville"},"a231601":{"bookmarkId":"231601","name":"Farm 049 022","isFavorite":"0","isFriendly":"0","isHostile":"0","tileId":"8517","xCoord":"49","yCoord":"22","tileLevel":"5","tileCityId":"25537","tileUserId":"40200","displayName":"Nameme","race":"1","cityId":"25537","cityUserId":"40200","cityName":"City"},"a235296":{"bookmarkId":"235296","name":"Tia2","isFavorite":"1","isFriendly":"0","isHostile":"0","tileId":"345197","xCoord":"140","yCoord":"457","tileLevel":"9","tileCityId":"119348","tileUserId":"887140","displayName":"Tia2","race":"1","cityId":"119348","cityUserId":"887140","cityName":"Tirion"},"a235554":{"bookmarkId":"235554","name":"Beasts no farm","isFavorite":"0","isFriendly":"1","isHostile":"0","tileId":"17065","xCoord":"93","yCoord":"55","tileLevel":"6","tileCityId":"158959","tileUserId":"3498752","displayName":"McCool","race":"1","cityId":"158959","cityUserId":"3498752","cityName":"Fresh"},"a235622":{"bookmarkId":"235622","name":"Farm 004 054 good","isFavorite":"0","isFriendly":"1","isHostile":"0","tileId":"869","xCoord":"4","yCoord":"54","tileLevel":"4","tileCityId":"91167","tileUserId":"234832","displayName":"Monty711","race":"2","cityId":"91167","cityUserId":"234832","cityName":"Avalon"},"a236452":{"bookmarkId":"236452","name":"Farm 099 119 good","isFavorite":"0","isFriendly":"1","isHostile":"0","tileId":"18394","xCoord":"99","yCoord":"119","tileLevel":"6","tileCityId":"29190","tileUserId":"52056","displayName":"Blake","race":"2","cityId":"29190","cityUserId":"52056","cityName":"NewCity1460"},"a236502":{"bookmarkId":"236502","name":"Tina","isFavorite":"1","isFriendly":"0","isHostile":"0","tileId":"36359","xCoord":"197","yCoord":"14","tileLevel":"1","tileCityId":"138777","tileUserId":"1069344","displayName":"Roni1999","race":"1","cityId":"138777","cityUserId":"1069344","cityName":"sulyman"},"a237457":{"bookmarkId":"237457","name":"Farm 127 152","isFavorite":"0","isFriendly":"0","isHostile":"0","tileId":"26957","xCoord":"127","yCoord":"152","tileLevel":"1","tileCityId":"38433","tileUserId":"77937","displayName":"Gman64","race":"1","cityId":"38433","cityUserId":"77937","cityName":"Gopolis"},"a237462":{"bookmarkId":"237462","name":"Farm 129 145","isFavorite":"0","isFriendly":"0","isHostile":"0","tileId":"26920","xCoord":"129","yCoord":"145","tileLevel":"6","tileCityId":"87662","tileUserId":"223328","displayName":"Mitrandil","race":"2","cityId":"87662","cityUserId":"223328","cityName":"Trimontium"},"a238270":{"bookmarkId":"238270","name":"Farm 006 033 close","isFavorite":"0","isFriendly":"1","isHostile":"0","tileId":"553","xCoord":"6","yCoord":"33","tileLevel":"5","tileCityId":"107625","tileUserId":"559896","displayName":"raygronas","race":"2","cityId":"107625","cityUserId":"559896","cityName":"Naboo"},"a238306":{"bookmarkId":"238306","name":"Mount","isFavorite":"1","isFriendly":"0","isHostile":"0","tileId":"165322","xCoord":"30","yCoord":"262","tileLevel":"1","tileCityId":"141529","tileUserId":"4004894","displayName":"NewUser-2DU72","race":"1","cityId":"141529","cityUserId":"4004894","cityName":"NewCity2DU72"},"a238557":{"bookmarkId":"238557","name":"No Farm whiskers","isFavorite":"0","isFriendly":"0","isHostile":"0","tileId":"25579","xCoord":"136","yCoord":"79","tileLevel":"1","tileCityId":"136824","tileUserId":"1548184","displayName":"Herkules","race":"2","cityId":"136824","cityUserId":"1548184","cityName":"Liselund"},"a238596":{"bookmarkId":"238596","name":"Farm 138 075 good","isFavorite":"0","isFriendly":"1","isHostile":"0","tileId":"25565","xCoord":"138","yCoord":"75","tileLevel":"6","tileCityId":"89008","tileUserId":"227440","displayName":"Cedars","race":"2","cityId":"89008","cityUserId":"227440","cityName":"BEIRUT"},"a238783":{"bookmarkId":"238783","name":"Whiskers prot","isFavorite":"0","isFriendly":"0","isHostile":"0","tileId":"23094","xCoord":"114","yCoord":"159","tileLevel":"2","tileCityId":"137952","tileUserId":"2932880","displayName":"Kasi007","race":"1","cityId":"137952","cityUserId":"2932880","cityName":"Kasi1982"},"a239549":{"bookmarkId":"239549","name":"Fuse","isFavorite":"0","isFriendly":"0","isHostile":"0","tileId":"38369","xCoord":"199","yCoord":"114","tileLevel":"9","tileCityId":"13175","tileUserId":"19984","displayName":"Alexash11","race":"2","cityId":"13175","cityUserId":"19984","cityName":"Rivendell"},"a239622":{"bookmarkId":"239622","name":"Farm 095 146 good","isFavorite":"0","isFriendly":"1","isHostile":"0","tileId":"19046","xCoord":"95","yCoord":"146","tileLevel":"6","tileCityId":"7179","tileUserId":"7088","displayName":"SquishtheBug","race":"2","cityId":"7179","cityUserId":"7088","cityName":"Delathron"},"a245202":{"bookmarkId":"245202","name":"Farm 044 006","isFavorite":"0","isFriendly":"0","isHostile":"0","tileId":"8041","xCoord":"44","yCoord":"6","tileLevel":"6","tileCityId":"126945","tileUserId":"1911712","displayName":"Tennessean","race":"2","cityId":"126945","cityUserId":"1911712","cityName":"Elvenheim"},"a245206":{"bookmarkId":"245206","name":"Farm 056 009","isFavorite":"0","isFriendly":"0","isHostile":"0","tileId":"8329","xCoord":"56","yCoord":"9","tileLevel":"6","tileCityId":"112454","tileUserId":"582864","displayName":"glorfinwood","race":"2","cityId":"112454","cityUserId":"582864","cityName":"NewCityCHQO"},"a245486":{"bookmarkId":"245486","name":"Farm 114 108","isFavorite":"0","isFriendly":"0","isHostile":"0","tileId":"22243","xCoord":"114","yCoord":"108","tileLevel":"7","tileCityId":"31754","tileUserId":"59432","displayName":"kurtisap37","race":"2","cityId":"31754","cityUserId":"59432","cityName":"Tropiandor"},"a247390":{"bookmarkId":"247390","name":"Davidus","isFavorite":"1","isFriendly":"1","isHostile":"0","tileId":"312744","xCoord":"779","yCoord":"229","tileLevel":"9","tileCityId":"100554","tileUserId":"260846","displayName":"Davidus","race":"2","cityId":"100554","cityUserId":"260846","cityName":"Feelathome"},"a248483":{"bookmarkId":"248483","name":"Fuse Helms Deep","isFavorite":"0","isFriendly":"0","isHostile":"0","tileId":"51990","xCoord":"258","yCoord":"200","tileLevel":"9","tileCityId":"132882","tileUserId":"2679819","displayName":"Thunderton","race":"1","cityId":"132882","cityUserId":"2679819","cityName":"Helms Deep"},"a251145":{"bookmarkId":"251145","name":"Tia2","isFavorite":"1","isFriendly":"0","isHostile":"0","tileId":"191636","xCoord":"143","yCoord":"386","tileLevel":"9","tileCityId":"136839","tileUserId":"887140","displayName":"Tia2","race":"1","cityId":"136839","cityUserId":"887140","cityName":"tirion2"},"a251174":{"bookmarkId":"251174","name":"Gilly","isFavorite":"1","isFriendly":"0","isHostile":"0","tileId":"167715","xCoord":"28","yCoord":"385","tileLevel":"9","tileCityId":"102178","tileUserId":"265807","displayName":"Gilly1965","race":"2","cityId":"102178","cityUserId":"265807","cityName":"Mcgillville"},"a251714":{"bookmarkId":"251714","name":"SirRaj","isFavorite":"1","isFriendly":"0","isHostile":"0","tileId":"325637","xCoord":"23","yCoord":"487","tileLevel":"9","tileCityId":"130800","tileUserId":"225831","displayName":"SirRajTheElf","race":"2","cityId":"130800","cityUserId":"225831","cityName":"Tia\\'s Lover"},"a251736":{"bookmarkId":"251736","name":"Zip","isFavorite":"1","isFriendly":"0","isHostile":"0","tileId":"291878","xCoord":"651","yCoord":"398","tileLevel":"10","tileCityId":"35867","tileUserId":"69699","displayName":"ZiptheKid","race":"2","cityId":"35867","cityUserId":"69699","cityName":"Zipsville"},"a252187":{"bookmarkId":"252187","name":"Llame","isFavorite":"1","isFriendly":"0","isHostile":"0","tileId":"116614","xCoord":"593","yCoord":"24","tileLevel":"9","tileCityId":"131651","tileUserId":"127602","displayName":"SaphireRules","race":"2","cityId":"131651","cityUserId":"127602","cityName":"Llamedos"},"a253257":{"bookmarkId":"253257","name":"Farm 151 002","isFavorite":"0","isFriendly":"0","isHostile":"0","tileId":"28202","xCoord":"151","yCoord":"2","tileLevel":"4","tileCityId":"124847","tileUserId":"1890624","displayName":"Viriathus","race":"2","cityId":"124847","cityUserId":"1890624","cityName":"Rome"},"a253532":{"bookmarkId":"253532","name":"Farm 160 028","isFavorite":"0","isFriendly":"0","isHostile":"0","tileId":"28748","xCoord":"160","yCoord":"28","tileLevel":"6","tileCityId":"24912","tileUserId":"38208","displayName":"Adelaide","race":"2","cityId":"24912","cityUserId":"38208","cityName":"NewCityTHC"},"a253557":{"bookmarkId":"253557","name":"Farm 048 052","isFavorite":"0","isFriendly":"0","isHostile":"0","tileId":"8962","xCoord":"48","yCoord":"52","tileLevel":"5","tileCityId":"88494","tileUserId":"225912","displayName":"Zey","race":"2","cityId":"88494","cityUserId":"225912","cityName":"NewCity4UBC"},"a253571":{"bookmarkId":"253571","name":"Farm 055 063","isFavorite":"0","isFriendly":"0","isHostile":"0","tileId":"9423","xCoord":"55","yCoord":"63","tileLevel":"6","tileCityId":"21128","tileUserId":"30032","displayName":"vegalomaniac","race":"2","cityId":"21128","cityUserId":"30032","cityName":"NewCityN68"},"a254087":{"bookmarkId":"254087","name":"Smithy","isFavorite":"1","isFriendly":"0","isHostile":"0","tileId":"351228","xCoord":"141","yCoord":"568","tileLevel":"9","tileCityId":"71654","tileUserId":"173449","displayName":"Smithy1992","race":"2","cityId":"71654","cityUserId":"173449","cityName":"Bishop World"},"a254196":{"bookmarkId":"254196","name":"Farm 219 237 good","isFavorite":"0","isFriendly":"0","isHostile":"0","tileId":"200792","xCoord":"219","yCoord":"237","tileLevel":"9","tileCityId":"40841","tileUserId":"85123","displayName":"Tannock","race":"2","cityId":"40841","cityUserId":"85123","cityName":"Gondolin"},"a255338":{"bookmarkId":"255338","name":"Farm 126 128 good","isFavorite":"0","isFriendly":"1","isHostile":"0","tileId":"26528","xCoord":"126","yCoord":"128","tileLevel":"7","tileCityId":"107928","tileUserId":"561944","displayName":"Wargoo","race":"1","cityId":"107928","cityUserId":"561944","cityName":"warrak"},"a256150":{"bookmarkId":"256150","name":"Titan","isFavorite":"0","isFriendly":"0","isHostile":"0","tileId":"606689","xCoord":"633","yCoord":"739","tileLevel":"9","tileCityId":"141446","tileUserId":"3988643","displayName":"HuIkSmash","race":"2","cityId":"141446","cityUserId":"3988643","cityName":"Metalville"},"a256689":{"bookmarkId":"256689","name":"Fuse 40 k might","isFavorite":"0","isFriendly":"0","isHostile":"0","tileId":"187759","xCoord":"127","yCoord":"394","tileLevel":"9","tileCityId":"74811","tileUserId":"184274","displayName":"Note","race":"2","cityId":"74811","cityUserId":"184274","cityName":"Notability"},"a256703":{"bookmarkId":"256703","name":"Fuse 4m mgt","isFavorite":"0","isFriendly":"0","isHostile":"0","tileId":"38335","xCoord":"197","yCoord":"110","tileLevel":"9","tileCityId":"28646","tileUserId":"50296","displayName":"faerileand","race":"2","cityId":"28646","cityUserId":"50296","cityName":"faerielvenland"},"a256729":{"bookmarkId":"256729","name":"Zip 2","isFavorite":"1","isFriendly":"0","isHostile":"0","tileId":"127689","xCoord":"623","yCoord":"199","tileLevel":"9","tileCityId":"135391","tileUserId":"69699","displayName":"ZiptheKid","race":"2","cityId":"135391","cityUserId":"69699","cityName":"Jethro Tull"},"a256740":{"bookmarkId":"256740","name":"Mountirontop","isFavorite":"1","isFriendly":"0","isHostile":"0","tileId":"67488","xCoord":"333","yCoord":"178","tileLevel":"10","tileCityId":"48341","tileUserId":"105932","displayName":"Mountironside","race":"1","cityId":"48341","cityUserId":"105932","cityName":"Mountirontop"},"a257466":{"bookmarkId":"257466","name":"Lance","isFavorite":"0","isFriendly":"0","isHostile":"0","tileId":"281564","xCoord":"618","yCoord":"274","tileLevel":"9","tileCityId":"133521","tileUserId":"2890337","displayName":"Lancaless","race":"2","cityId":"133521","cityUserId":"2890337","cityName":"Ballcrusher"},"a257475":{"bookmarkId":"257475","name":"Fulgrimator","isFavorite":"0","isFriendly":"1","isHostile":"0","tileId":"169427","xCoord":"51","yCoord":"267","tileLevel":"5","tileCityId":"141620","tileUserId":"1205678","displayName":"fulgrimator","race":"2","cityId":"141620","cityUserId":"1205678","cityName":"YourFcked"},"a258303":{"bookmarkId":"258303","name":"Tina 2","isFavorite":"1","isFriendly":"0","isHostile":"0","tileId":"70465","xCoord":"343","yCoord":"135","tileLevel":"1","tileCityId":"0","tileUserId":"0","displayName":"","race":"","cityId":"","cityUserId":"","cityName":""},"a259768":{"bookmarkId":"259768","name":"Halfling 107 411","isFavorite":"0","isFriendly":"0","isHostile":"0","tileId":"340156","xCoord":"107","yCoord":"411","tileLevel":"9","tileCityId":"114893","tileUserId":"247854","displayName":"Franticbliss","race":"2","cityId":"114893","cityUserId":"247854","cityName":"DroopylipHobbit"},"a261211":{"bookmarkId":"261211","name":"Oldshady","isFavorite":"1","isFriendly":"0","isHostile":"0","tileId":"280395","xCoord":"619","yCoord":"220","tileLevel":"1","tileCityId":"144671","tileUserId":"4176115","displayName":"casey12","race":"2","cityId":"144671","cityUserId":"4176115","cityName":"NewCity2HIB7"},"a261507":{"bookmarkId":"261507","name":"Halfling 604 138","isFavorite":"0","isFriendly":"0","isHostile":"0","tileId":"122493","xCoord":"604","yCoord":"138","tileLevel":"9","tileCityId":"107109","tileUserId":"272671","displayName":"Qwote","race":"1","cityId":"107109","cityUserId":"272671","cityName":"ExtraLubePlease"},"a262248":{"bookmarkId":"262248","name":"Farm 104 127","isFavorite":"0","isFriendly":"0","isHostile":"0","tileId":"22442","xCoord":"104","yCoord":"127","tileLevel":"1","tileCityId":"90371","tileUserId":"232284","displayName":"Melly12345","race":"2","cityId":"90371","cityUserId":"232284","cityName":"Dragonhelm"},"a262678":{"bookmarkId":"262678","name":"Farm 078 035","isFavorite":"0","isFriendly":"0","isHostile":"0","tileId":"12765","xCoord":"78","yCoord":"35","tileLevel":"5","tileCityId":"138597","tileUserId":"3866112","displayName":"Hatchethead","race":"1","cityId":"138597","cityUserId":"3866112","cityName":"The Homestead"},"a262682":{"bookmarkId":"262682","name":"Farm 084 036","isFavorite":"0","isFriendly":"0","isHostile":"0","tileId":"16491","xCoord":"84","yCoord":"36","tileLevel":"4","tileCityId":"89643","tileUserId":"229676","displayName":"Morgrn","race":"2","cityId":"89643","cityUserId":"229676","cityName":"NewCity4X7W"},"a262708":{"bookmarkId":"262708","name":"Sulton","isFavorite":"1","isFriendly":"0","isHostile":"0","tileId":"465787","xCoord":"728","yCoord":"497","tileLevel":"9","tileCityId":"265","tileUserId":"264","displayName":"Sulton","race":"2","cityId":"265","cityUserId":"264","cityName":"Elfbane"},"a263630":{"bookmarkId":"263630","name":"Farm 037 122 good","isFavorite":"0","isFriendly":"1","isHostile":"0","tileId":"6707","xCoord":"37","yCoord":"122","tileLevel":"5","tileCityId":"87234","tileUserId":"222164","displayName":"Zaachh","race":"2","cityId":"87234","cityUserId":"222164","cityName":"Kingsway"},"a263660":{"bookmarkId":"263660","name":"Farm 036 146 good","isFavorite":"0","isFriendly":"1","isHostile":"0","tileId":"7126","xCoord":"36","yCoord":"146","tileLevel":"9","tileCityId":"99","tileUserId":"99","displayName":"Gondor","race":"2","cityId":"99","cityUserId":"99","cityName":"Gondor"},"a263717":{"bookmarkId":"263717","name":"Farm 042 145 good","isFavorite":"0","isFriendly":"1","isHostile":"0","tileId":"10810","xCoord":"42","yCoord":"145","tileLevel":"5","tileCityId":"83248","tileUserId":"210736","displayName":"Bolbadil","race":"2","cityId":"83248","cityUserId":"210736","cityName":"Skyfall"},"a263723":{"bookmarkId":"263723","name":"Farm 038 129","isFavorite":"0","isFriendly":"0","isHostile":"0","tileId":"6739","xCoord":"38","yCoord":"129","tileLevel":"4","tileCityId":"118561","tileUserId":"574704","displayName":"Thelonia","race":"1","cityId":"118561","cityUserId":"574704","cityName":"Sparta"},"a263728":{"bookmarkId":"263728","name":"Farm 041 110","isFavorite":"0","isFriendly":"0","isHostile":"0","tileId":"10030","xCoord":"41","yCoord":"110","tileLevel":"4","tileCityId":"17485","tileUserId":"25904","displayName":"CaptRobbie","race":"2","cityId":"17485","cityUserId":"25904","cityName":"NewCityJZK"},"a263765":{"bookmarkId":"263765","name":"Farm 063 105 food","isFavorite":"0","isFriendly":"1","isHostile":"0","tileId":"14015","xCoord":"63","yCoord":"105","tileLevel":"5","tileCityId":"129772","tileUserId":"1360120","displayName":"Jalomount","race":"1","cityId":"129772","cityUserId":"1360120","cityName":"Wulkerz"},"a263787":{"bookmarkId":"263787","name":"Farm 079 079 good","isFavorite":"0","isFriendly":"1","isHostile":"0","tileId":"13594","xCoord":"79","yCoord":"79","tileLevel":"6","tileCityId":"53222","tileUserId":"117408","displayName":"Caashe","race":"2","cityId":"53222","cityUserId":"117408","cityName":"Cityofchaos"},"a263805":{"bookmarkId":"263805","name":"Farm 086 075","isFavorite":"0","isFriendly":"0","isHostile":"0","tileId":"17355","xCoord":"86","yCoord":"75","tileLevel":"4","tileCityId":"78899","tileUserId":"195200","displayName":"Pap","race":"2","cityId":"78899","cityUserId":"195200","cityName":"NewCity46M8"},"a264098":{"bookmarkId":"264098","name":"Farm 072 052 good","isFavorite":"0","isFriendly":"1","isHostile":"0","tileId":"13057","xCoord":"72","yCoord":"52","tileLevel":"5","tileCityId":"62855","tileUserId":"148064","displayName":"MasterNico","race":"2","cityId":"62855","cityUserId":"148064","cityName":"Mightykingdom"},"a265438":{"bookmarkId":"265438","name":"RepublicOfIreland","isFavorite":"1","isFriendly":"0","isHostile":"0","tileId":"336236","xCoord":"93","yCoord":"406","tileLevel":"9","tileCityId":"83733","tileUserId":"212533","displayName":"Republicireland","race":"2","cityId":"83733","cityUserId":"212533","cityName":"Shane"},"a266004":{"bookmarkId":"266004","name":"Farm 133 033","isFavorite":"0","isFriendly":"0","isHostile":"0","tileId":"24663","xCoord":"133","yCoord":"33","tileLevel":"4","tileCityId":"71087","tileUserId":"171440","displayName":"aluria","race":"2","cityId":"71087","cityUserId":"171440","cityName":"esthrem"},"a267426":{"bookmarkId":"267426","name":"Halfling 021 235","isFavorite":"0","isFriendly":"0","isHostile":"0","tileId":"164455","xCoord":"21","yCoord":"235","tileLevel":"9","tileCityId":"26023","tileUserId":"41846","displayName":"Katevini","race":"2","cityId":"26023","cityUserId":"41846","cityName":"Harberidge"},"a267548":{"bookmarkId":"267548","name":"Farm 140 197","isFavorite":"0","isFriendly":"0","isHostile":"0","tileId":"27997","xCoord":"140","yCoord":"197","tileLevel":"8","tileCityId":"72362","tileUserId":"175888","displayName":"swedishrose","race":"2","cityId":"72362","cityUserId":"175888","cityName":"elvish waters"},"a267597":{"bookmarkId":"267597","name":"Farm 137 136","isFavorite":"0","isFriendly":"0","isHostile":"0","tileId":"26781","xCoord":"137","yCoord":"136","tileLevel":"3","tileCityId":"131632","tileUserId":"1809000","displayName":"Ladendel","race":"2","cityId":"131632","cityUserId":"1809000","cityName":"NewCity12RU0"},"a267599":{"bookmarkId":"267599","name":"Farm 146 172","isFavorite":"0","isFriendly":"0","isHostile":"0","tileId":"31352","xCoord":"146","yCoord":"172","tileLevel":"4","tileCityId":"131534","tileUserId":"897028","displayName":"walhalla2","race":"2","cityId":"131534","cityUserId":"897028","cityName":"NewCityJ85G"},"a267677":{"bookmarkId":"267677","name":"Farm 149 168","isFavorite":"0","isFriendly":"0","isHostile":"0","tileId":"31343","xCoord":"149","yCoord":"168","tileLevel":"6","tileCityId":"90479","tileUserId":"232580","displayName":"YoungGun","race":"1","cityId":"90479","cityUserId":"232580","cityName":"YoungGunCity"},"a267680":{"bookmarkId":"267680","name":"Farm 150 161","isFavorite":"0","isFriendly":"0","isHostile":"0","tileId":"31321","xCoord":"150","yCoord":"161","tileLevel":"8","tileCityId":"22845","tileUserId":"32048","displayName":"Weedz","race":"2","cityId":"22845","cityUserId":"32048","cityName":"Weedonia"},"a270494":{"bookmarkId":"270494","name":"Farm 153 081","isFavorite":"0","isFriendly":"0","isHostile":"0","tileId":"29811","xCoord":"153","yCoord":"81","tileLevel":"3","tileCityId":"43819","tileUserId":"93568","displayName":"Ackbeard","race":"1","cityId":"43819","cityUserId":"93568","cityName":"NewCity2074"},"a270503":{"bookmarkId":"270503","name":"Farm 159 059","isFavorite":"0","isFriendly":"0","isHostile":"0","tileId":"29194","xCoord":"159","yCoord":"59","tileLevel":"2","tileCityId":"73497","tileUserId":"179912","displayName":"Cirdane","race":"2","cityId":"73497","cityUserId":"179912","cityName":"Valinor"},"a273602":{"bookmarkId":"273602","name":"Farm 111 191","isFavorite":"0","isFriendly":"0","isHostile":"0","tileId":"23851","xCoord":"111","yCoord":"191","tileLevel":"4","tileCityId":"128873","tileUserId":"1932288","displayName":"Satie","race":"1","cityId":"128873","cityUserId":"1932288","cityName":"New Dale"},"a273604":{"bookmarkId":"273604","name":"Farm 114 184","isFavorite":"0","isFriendly":"0","isHostile":"0","tileId":"23819","xCoord":"114","yCoord":"184","tileLevel":"2","tileCityId":"5731","tileUserId":"5664","displayName":"Markarth","race":"1","cityId":"5731","cityUserId":"5664","cityName":"NewCity4DC"},"a273607":{"bookmarkId":"273607","name":"Farm 115 183 good","isFavorite":"0","isFriendly":"1","isHostile":"0","tileId":"23823","xCoord":"115","yCoord":"183","tileLevel":"5","tileCityId":"96713","tileUserId":"251024","displayName":"NightHawk02","race":"2","cityId":"96713","cityUserId":"251024","cityName":"Edgarton"},"a273608":{"bookmarkId":"273608","name":"Farm 112 178 good","isFavorite":"0","isFriendly":"1","isHostile":"0","tileId":"23483","xCoord":"112","yCoord":"178","tileLevel":"6","tileCityId":"121638","tileUserId":"1548032","displayName":"rasta_man","race":"2","cityId":"121638","cityUserId":"1548032","cityName":"zion"},"a273911":{"bookmarkId":"273911","name":"Farm 149 072","isFavorite":"0","isFriendly":"0","isHostile":"0","tileId":"29367","xCoord":"149","yCoord":"72","tileLevel":"4","tileCityId":"56394","tileUserId":"127984","displayName":"StoneIsland","race":"2","cityId":"56394","cityUserId":"127984","cityName":"StoneIsland"},"a273941":{"bookmarkId":"273941","name":"StigsUncle","isFavorite":"1","isFriendly":"0","isHostile":"0","tileId":"194250","xCoord":"175","yCoord":"310","tileLevel":"9","tileCityId":"120444","tileUserId":"948606","displayName":"StigsUncle","race":"2","cityId":"120444","cityUserId":"948606","cityName":"Realm of Stig"},"a273945":{"bookmarkId":"273945","name":"Farm 174 054","isFavorite":"0","isFriendly":"0","isHostile":"0","tileId":"33069","xCoord":"174","yCoord":"54","tileLevel":"4","tileCityId":"120821","tileUserId":"1544544","displayName":"Windamire","race":"2","cityId":"120821","cityUserId":"1544544","cityName":"NewCityX3S0"},"a274068":{"bookmarkId":"274068","name":"Halfling 620 396","isFavorite":"0","isFriendly":"0","isHostile":"0","tileId":"283996","xCoord":"620","yCoord":"396","tileLevel":"10","tileCityId":"123972","tileUserId":"1817426","displayName":"Kierandun","race":"1","cityId":"123972","cityUserId":"1817426","cityName":"Belegost"},"a274074":{"bookmarkId":"274074","name":"Halfling 325 649","isFavorite":"0","isFriendly":"0","isHostile":"0","tileId":"544849","xCoord":"325","yCoord":"649","tileLevel":"1","tileCityId":"154911","tileUserId":"3315661","displayName":"Awesomesauce123","race":"2","cityId":"154911","cityUserId":"3315661","cityName":"Thorinsawesome"},"a274075":{"bookmarkId":"274075","name":"Halfling 324 648","isFavorite":"0","isFriendly":"0","isHostile":"0","tileId":"544843","xCoord":"324","yCoord":"648","tileLevel":"9","tileCityId":"3638","tileUserId":"1784","displayName":"R3DG1ANT","race":"1","cityId":"3638","cityUserId":"1784","cityName":"PropertyOfL4DY"},"a274079":{"bookmarkId":"274079","name":"Halfling 635 079","isFavorite":"0","isFriendly":"0","isHostile":"0","tileId":"125499","xCoord":"635","yCoord":"79","tileLevel":"3","tileCityId":"0","tileUserId":"0","displayName":"","race":"","cityId":"","cityUserId":"","cityName":""},"a274080":{"bookmarkId":"274080","name":"Halfling 104 360","isFavorite":"0","isFriendly":"0","isHostile":"0","tileId":"182895","xCoord":"104","yCoord":"360","tileLevel":"10","tileCityId":"129868","tileUserId":"1817426","displayName":"Kierandun","race":"1","cityId":"129868","cityUserId":"1817426","cityName":"Moria"},"a274081":{"bookmarkId":"274081","name":"Halfling 106 360","isFavorite":"0","isFriendly":"0","isHostile":"0","tileId":"182980","xCoord":"106","yCoord":"360","tileLevel":"10","tileCityId":"8582","tileUserId":"10164","displayName":"Andyj1992","race":"2","cityId":"8582","cityUserId":"10164","cityName":"Atlantis"},"a274143":{"bookmarkId":"274143","name":"Halfling 572 176","isFavorite":"0","isFriendly":"0","isHostile":"0","tileId":"115481","xCoord":"572","yCoord":"176","tileLevel":"3","tileCityId":"0","tileUserId":"0","displayName":"","race":"","cityId":"","cityUserId":"","cityName":""},"a274145":{"bookmarkId":"274145","name":"Halfling 572 173","isFavorite":"0","isFriendly":"0","isHostile":"0","tileId":"115458","xCoord":"572","yCoord":"173","tileLevel":"9","tileCityId":"71913","tileUserId":"174201","displayName":"Guccimain","race":"1","cityId":"71913","cityUserId":"174201","cityName":"Arkham"},"a274452":{"bookmarkId":"274452","name":"Llame 2","isFavorite":"0","isFriendly":"0","isHostile":"0","tileId":"116518","xCoord":"589","yCoord":"23","tileLevel":"10","tileCityId":"56297","tileUserId":"127602","displayName":"SaphireRules","race":"2","cityId":"56297","cityUserId":"127602","cityName":"Llamedos"},"a274488":{"bookmarkId":"274488","name":"Farm 176 094","isFavorite":"0","isFriendly":"0","isHostile":"0","tileId":"33954","xCoord":"176","yCoord":"94","tileLevel":"4","tileCityId":"89488","tileUserId":"229240","displayName":"Johnski99","race":"2","cityId":"89488","cityUserId":"229240","cityName":"NewCity4WVS"},"a275321":{"bookmarkId":"275321","name":"Farm 760 153","isFavorite":"0","isFriendly":"0","isHostile":"0","tileId":"151173","xCoord":"760","yCoord":"153","tileLevel":"5","tileCityId":"82157","tileUserId":"206593","displayName":"Pagan6a6y","race":"2","cityId":"82157","cityUserId":"206593","cityName":"Basslandia"},"a275853":{"bookmarkId":"275853","name":"Halfling 322 602","isFavorite":"0","isFriendly":"0","isHostile":"0","tileId":"544007","xCoord":"322","yCoord":"602","tileLevel":"9","tileCityId":"135592","tileUserId":"2126955","displayName":"Erabus","race":"2","cityId":"135592","cityUserId":"2126955","cityName":"Era2"},"a276193":{"bookmarkId":"276193","name":"Halfling 020 234","isFavorite":"0","isFriendly":"0","isHostile":"0","tileId":"160774","xCoord":"20","yCoord":"234","tileLevel":"5","tileCityId":"137198","tileUserId":"41846","displayName":"Katevini","race":"2","cityId":"137198","cityUserId":"41846","cityName":"Hegemony"},"a276196":{"bookmarkId":"276196","name":"Halfling 106 409","isFavorite":"0","isFriendly":"0","isHostile":"0","tileId":"340129","xCoord":"106","yCoord":"409","tileLevel":"10","tileCityId":"95487","tileUserId":"247854","displayName":"Franticbliss","race":"2","cityId":"95487","cityUserId":"247854","cityName":"Vindication"},"a277394":{"bookmarkId":"277394","name":"Halfling 057 796","isFavorite":"0","isFriendly":"0","isHostile":"0","tileId":"491981","xCoord":"57","yCoord":"796","tileLevel":"10","tileCityId":"48845","tileUserId":"107138","displayName":"BlackJesus","race":"2","cityId":"48845","cityUserId":"107138","cityName":"Drugs and Hoes"},"a277521":{"bookmarkId":"277521","name":"Farm 114 124","isFavorite":"0","isFriendly":"0","isHostile":"0","tileId":"22619","xCoord":"114","yCoord":"124","tileLevel":"8","tileCityId":"109091","tileUserId":"567485","displayName":"Elimayo","race":"2","cityId":"109091","cityUserId":"567485","cityName":"Puryear"},"a278596":{"bookmarkId":"278596","name":"Quix Sands","isFavorite":"1","isFriendly":"0","isHostile":"0","tileId":"40224","xCoord":"215","yCoord":"4","tileLevel":"9","tileCityId":"100200","tileUserId":"259789","displayName":"Quixotia","race":"2","cityId":"100200","cityUserId":"259789","cityName":"Quix Sands"},"a278597":{"bookmarkId":"278597","name":"Quixotia","isFavorite":"1","isFriendly":"0","isHostile":"0","tileId":"40221","xCoord":"215","yCoord":"1","tileLevel":"9","tileCityId":"120269","tileUserId":"259789","displayName":"Quixotia","race":"2","cityId":"120269","cityUserId":"259789","cityName":"Lythand"},"a278877":{"bookmarkId":"278877","name":"Farm 139 152","isFavorite":"0","isFriendly":"0","isHostile":"0","tileId":"27167","xCoord":"139","yCoord":"152","tileLevel":"4","tileCityId":"107872","tileUserId":"561080","displayName":"Toddlaaaa","race":"2","cityId":"107872","cityUserId":"561080","cityName":"Rivendell"},"a278882":{"bookmarkId":"278882","name":"Farm 140 151","isFavorite":"0","isFriendly":"0","isHostile":"0","tileId":"27171","xCoord":"140","yCoord":"151","tileLevel":"4","tileCityId":"41769","tileUserId":"87584","displayName":"Cityofwonder","race":"2","cityId":"41769","cityUserId":"87584","cityName":"Wonder city"},"a280426":{"bookmarkId":"280426","name":"Halfling 026 084","isFavorite":"0","isFriendly":"0","isHostile":"0","tileId":"5704","xCoord":"26","yCoord":"84","tileLevel":"9","tileCityId":"86882","tileUserId":"221339","displayName":"Cucci","race":"2","cityId":"86882","cityUserId":"221339","cityName":"NewCity4QSB"},"a280443":{"bookmarkId":"280443","name":"Jaspertown2","isFavorite":"1","isFriendly":"0","isHostile":"0","tileId":"170874","xCoord":"45","yCoord":"354","tileLevel":"9","tileCityId":"80126","tileUserId":"47310","displayName":"Jaspertown","race":"2","cityId":"80126","cityUserId":"47310","cityName":"Jaspertown2"},"a280445":{"bookmarkId":"280445","name":"Arias'tama","isFavorite":"1","isFriendly":"0","isHostile":"0","tileId":"182438","xCoord":"103","yCoord":"328","tileLevel":"9","tileCityId":"10303","tileUserId":"14392","displayName":"Arias'tama","race":"2","cityId":"10303","cityUserId":"14392","cityName":"Robins Hood"},"a280447":{"bookmarkId":"280447","name":"PrincessPopper","isFavorite":"1","isFriendly":"0","isHostile":"0","tileId":"351277","xCoord":"141","yCoord":"577","tileLevel":"1","tileCityId":"149084","tileUserId":"4275765","displayName":"NewUser-2JN79","race":"2","cityId":"149084","cityUserId":"4275765","cityName":"NewCity2JN79"},"a280451":{"bookmarkId":"280451","name":"Lasir","isFavorite":"1","isFriendly":"0","isHostile":"0","tileId":"583970","xCoord":"519","yCoord":"795","tileLevel":"9","tileCityId":"5008","tileUserId":"4946","displayName":"Lasir","race":"2","cityId":"5008","cityUserId":"4946","cityName":"Ellinia"},"a280459":{"bookmarkId":"280459","name":"BeeHunter","isFavorite":"1","isFriendly":"0","isHostile":"0","tileId":"376802","xCoord":"281","yCoord":"442","tileLevel":"9","tileCityId":"3682","tileUserId":"3637","displayName":"Beehunter","race":"1","cityId":"3682","cityUserId":"3637","cityName":"Belegost"},"a280461":{"bookmarkId":"280461","name":"Nebraska","isFavorite":"1","isFriendly":"0","isHostile":"0","tileId":"152795","xCoord":"779","yCoord":"40","tileLevel":"9","tileCityId":"33101","tileUserId":"62687","displayName":"Nebraska","race":"2","cityId":"33101","cityUserId":"62687","cityName":"Nebraska"},"a280634":{"bookmarkId":"280634","name":"War bunniYphrum","isFavorite":"0","isFriendly":"0","isHostile":"0","tileId":"174092","xCoord":"64","yCoord":"317","tileLevel":"9","tileCityId":"135166","tileUserId":"3128948","displayName":"Yphrum","race":"1","cityId":"135166","cityUserId":"3128948","cityName":"Yphrum"},"a281250":{"bookmarkId":"281250","name":"Farm 119 077","isFavorite":"0","isFriendly":"0","isHostile":"0","tileId":"21592","xCoord":"119","yCoord":"77","tileLevel":"4","tileCityId":"88484","tileUserId":"225796","displayName":"Juned","race":"2","cityId":"88484","cityUserId":"225796","cityName":"Rack city"},"a282964":{"bookmarkId":"282964","name":"Bank","isFavorite":"1","isFriendly":"0","isHostile":"0","tileId":"67464","xCoord":"333","yCoord":"174","tileLevel":"9","tileCityId":"133105","tileUserId":"2754519","displayName":"Mount","race":"1","cityId":"133105","cityUserId":"2754519","cityName":"NewCity1N1EF"},"a284248":{"bookmarkId":"284248","name":"Farm 035 091","isFavorite":"0","isFriendly":"0","isHostile":"0","tileId":"5871","xCoord":"35","yCoord":"91","tileLevel":"3","tileCityId":"95173","tileUserId":"246940","displayName":"Rivian","race":"1","cityId":"95173","cityUserId":"246940","cityName":"Iron Hills"},"a284653":{"bookmarkId":"284653","name":"Farm 090 162","isFavorite":"0","isFriendly":"0","isHostile":"0","tileId":"19322","xCoord":"90","yCoord":"162","tileLevel":"7","tileCityId":"96929","tileUserId":"251560","displayName":"Mr_Hammy","race":"1","cityId":"96929","cityUserId":"251560","cityName":"Hammykeep"},"a284845":{"bookmarkId":"284845","name":"Farm 091 045","isFavorite":"0","isFriendly":"0","isHostile":"0","tileId":"17005","xCoord":"91","yCoord":"45","tileLevel":"4","tileCityId":"109062","tileUserId":"567440","displayName":"Siskingdom","race":"2","cityId":"109062","cityUserId":"567440","cityName":"NewCityC5U8"},"a284866":{"bookmarkId":"284866","name":"Farm 088 144","isFavorite":"0","isFriendly":"0","isHostile":"0","tileId":"18914","xCoord":"88","yCoord":"144","tileLevel":"5","tileCityId":"112261","tileUserId":"582112","displayName":"MungoMaggot","race":"1","cityId":"112261","cityUserId":"582112","cityName":"Samitor"},"a286193":{"bookmarkId":"286193","name":"Farm 007 037","isFavorite":"0","isFriendly":"0","isHostile":"0","tileId":"582","xCoord":"7","yCoord":"37","tileLevel":"5","tileCityId":"58727","tileUserId":"135088","displayName":"Matyas","race":"1","cityId":"58727","cityUserId":"135088","cityName":"NewCity2W8G"},"a286215":{"bookmarkId":"286215","name":"Farm 207 122","isFavorite":"0","isFriendly":"0","isHostile":"0","tileId":"42507","xCoord":"207","yCoord":"122","tileLevel":"6","tileCityId":"31964","tileUserId":"59879","displayName":"Benjiebop","race":"2","cityId":"31964","cityUserId":"59879","cityName":"NewCity1A7B"},"a286265":{"bookmarkId":"286265","name":"Farm 003 032","isFavorite":"0","isFriendly":"0","isHostile":"0","tileId":"462","xCoord":"3","yCoord":"32","tileLevel":"7","tileCityId":"32351","tileUserId":"60912","displayName":"woodville","race":"1","cityId":"32351","cityUserId":"60912","cityName":"Farrelno"},"a286325":{"bookmarkId":"286325","name":"Farm 206 108","isFavorite":"0","isFriendly":"0","isHostile":"0","tileId":"42128","xCoord":"206","yCoord":"108","tileLevel":"7","tileCityId":"31007","tileUserId":"57447","displayName":"Aphrodite","race":"2","cityId":"31007","cityUserId":"57447","cityName":"Underhill"},"a286654":{"bookmarkId":"286654","name":"Farm 797 006 awesome","isFavorite":"0","isFriendly":"0","isHostile":"0","tileId":"156331","xCoord":"797","yCoord":"6","tileLevel":"8","tileCityId":"7270","tileUserId":"7176","displayName":"V13","race":"2","cityId":"7270","cityUserId":"7176","cityName":"Quebec"},"a286732":{"bookmarkId":"286732","name":"Farm 299 097","isFavorite":"0","isFriendly":"0","isHostile":"0","tileId":"57992","xCoord":"299","yCoord":"97","tileLevel":"9","tileCityId":"18054","tileUserId":"26565","displayName":"Daigo","race":"2","cityId":"18054","cityUserId":"26565","cityName":"Daggers"},"a286734":{"bookmarkId":"286734","name":"Farm 299 107","isFavorite":"0","isFriendly":"0","isHostile":"0","tileId":"58342","xCoord":"299","yCoord":"107","tileLevel":"9","tileCityId":"90217","tileUserId":"231719","displayName":"Siepie","race":"2","cityId":"90217","cityUserId":"231719","cityName":"Summerfall"},"a286754":{"bookmarkId":"286754","name":"Muffy 2","isFavorite":"1","isFriendly":"0","isHostile":"0","tileId":"197523","xCoord":"200","yCoord":"263","tileLevel":"1","tileCityId":"162079","tileUserId":"5184222","displayName":"NewUser-33466","race":"2","cityId":"162079","cityUserId":"5184222","cityName":"NewCity33466"},"a287099":{"bookmarkId":"287099","name":"Halfling 056 793","isFavorite":"0","isFriendly":"0","isHostile":"0","tileId":"491953","xCoord":"56","yCoord":"793","tileLevel":"8","tileCityId":"147188","tileUserId":"4112403","displayName":"Voidrin","race":"2","cityId":"147188","cityUserId":"4112403","cityName":"Voidtoss"},"a287102":{"bookmarkId":"287102","name":"Halfling 056 789","isFavorite":"0","isFriendly":"0","isHostile":"0","tileId":"491929","xCoord":"56","yCoord":"789","tileLevel":"9","tileCityId":"145788","tileUserId":"4201200","displayName":"Bill_Nye","race":"1","cityId":"145788","cityUserId":"4201200","cityName":"A Punch Villa"},"a291032":{"bookmarkId":"291032","name":"Halfling 715 738","isFavorite":"0","isFriendly":"0","isHostile":"0","tileId":"622698","xCoord":"715","yCoord":"738","tileLevel":"8","tileCityId":"0","tileUserId":"0","displayName":"","race":"","cityId":"","cityUserId":"","cityName":""},"a291889":{"bookmarkId":"291889","name":"Halfling 200 600","isFavorite":"0","isFriendly":"0","isHostile":"0","tileId":"360000","xCoord":"200","yCoord":"600","tileLevel":"9","tileCityId":"1540","tileUserId":"1528","displayName":"BETTYWHITE","race":"2","cityId":"1540","cityUserId":"1528","cityName":"A dirty vag"},"a291892":{"bookmarkId":"291892","name":"Halfling 201 610","isFavorite":"0","isFriendly":"0","isHostile":"0","tileId":"520030","xCoord":"201","yCoord":"610","tileLevel":"10","tileCityId":"101828","tileUserId":"264705","displayName":"b0lstad","race":"2","cityId":"101828","cityUserId":"264705","cityName":"City of ASO"},"a291893":{"bookmarkId":"291893","name":"Halfling 202 610","isFavorite":"0","isFriendly":"0","isHostile":"0","tileId":"520035","xCoord":"202","yCoord":"610","tileLevel":"9","tileCityId":"135772","tileUserId":"264705","displayName":"b0lstad","race":"2","cityId":"135772","cityUserId":"264705","cityName":"Little Norway"},"a292408":{"bookmarkId":"292408","name":"Halfling 151 236","isFavorite":"0","isFriendly":"0","isHostile":"0","tileId":"188676","xCoord":"151","yCoord":"236","tileLevel":"9","tileCityId":"48248","tileUserId":"33859","displayName":"Egwene","race":"2","cityId":"48248","cityUserId":"33859","cityName":"The White Tower"},"a292409":{"bookmarkId":"292409","name":"Halfling 149 236","isFavorite":"0","isFriendly":"0","isHostile":"0","tileId":"188591","xCoord":"149","yCoord":"236","tileLevel":"10","tileCityId":"117441","tileUserId":"1011765","displayName":"Crimsonquaker","race":"2","cityId":"117441","cityUserId":"1011765","cityName":"Buena vista"},"a292413":{"bookmarkId":"292413","name":"Halfling 148 237","isFavorite":"0","isFriendly":"0","isHostile":"0","tileId":"188587","xCoord":"148","yCoord":"237","tileLevel":"9","tileCityId":"134564","tileUserId":"1011765","displayName":"Crimsonquaker","race":"2","cityId":"134564","cityUserId":"1011765","cityName":"Lothlorien"},"a292555":{"bookmarkId":"292555","name":"Jasper 3","isFavorite":"1","isFriendly":"0","isHostile":"0","tileId":"316012","xCoord":"783","yCoord":"202","tileLevel":"9","tileCityId":"133668","tileUserId":"2935849","displayName":"Jaspertown3","race":"2","cityId":"133668","cityUserId":"2935849","cityName":"Le Dieu"},"a295842":{"bookmarkId":"295842","name":"Halfling 014 761","isFavorite":"0","isFriendly":"0","isHostile":"0","tileId":"483416","xCoord":"14","yCoord":"761","tileLevel":"9","tileCityId":"131407","tileUserId":"2366372","displayName":"pimpmaster","race":"1","cityId":"131407","cityUserId":"2366372","cityName":"white trash lan"},"a295843":{"bookmarkId":"295843","name":"Halfling 017 775","isFavorite":"0","isFriendly":"0","isHostile":"0","tileId":"483560","xCoord":"17","yCoord":"775","tileLevel":"8","tileCityId":"0","tileUserId":"0","displayName":"","race":"","cityId":"","cityUserId":"","cityName":""},"a299077":{"bookmarkId":"299077","name":"Farm 104 129 good","isFavorite":"0","isFriendly":"1","isHostile":"0","tileId":"22444","xCoord":"104","yCoord":"129","tileLevel":"8","tileCityId":"101648","tileUserId":"264112","displayName":"Fox_of_the_Mist","race":"1","cityId":"101648","cityUserId":"264112","cityName":"Hidden Mist"},"a299642":{"bookmarkId":"299642","name":"Farm 116 124","isFavorite":"0","isFriendly":"0","isHostile":"0","tileId":"22704","xCoord":"116","yCoord":"124","tileLevel":"9","tileCityId":"98688","tileUserId":"255696","displayName":"MrCaboose","race":"2","cityId":"98688","cityUserId":"255696","cityName":"The wall"},"a299644":{"bookmarkId":"299644","name":"Farm 117 119","isFavorite":"0","isFriendly":"0","isHostile":"0","tileId":"22384","xCoord":"117","yCoord":"119","tileLevel":"5","tileCityId":"11359","tileUserId":"16704","displayName":"Eodyn","race":"2","cityId":"11359","cityUserId":"16704","cityName":"Eodyn's city"},"a299657":{"bookmarkId":"299657","name":"Farm 112 100","isFavorite":"0","isFriendly":"0","isHostile":"0","tileId":"21885","xCoord":"112","yCoord":"100","tileLevel":"8","tileCityId":"94162","tileUserId":"243819","displayName":"Kellbo","race":"2","cityId":"94162","cityUserId":"243819","cityName":"NewCity584R"},"a300355":{"bookmarkId":"300355","name":"Halfling 200 474","isFavorite":"0","isFriendly":"0","isHostile":"0","tileId":"357574","xCoord":"200","yCoord":"474","tileLevel":"10","tileCityId":"7546","tileUserId":"7448","displayName":"SoulSister","race":"2","cityId":"7546","cityUserId":"7448","cityName":"Don't You Dare"},"a300554":{"bookmarkId":"300554","name":"Halfling 199 478","isFavorite":"0","isFriendly":"0","isHostile":"0","tileId":"357593","xCoord":"199","yCoord":"478","tileLevel":"8","tileCityId":"135725","tileUserId":"7448","displayName":"SoulSister","race":"2","cityId":"135725","cityUserId":"7448","cityName":"Pointless"},"a301476":{"bookmarkId":"301476","name":"Farm 009 065","isFavorite":"0","isFriendly":"0","isHostile":"0","tileId":"1320","xCoord":"9","yCoord":"65","tileLevel":"4","tileCityId":"131154","tileUserId":"2336784","displayName":"Sup4m0nkey","race":"2","cityId":"131154","cityUserId":"2336784","cityName":"Minas Uzul"},"a301482":{"bookmarkId":"301482","name":"Farm 010 068","isFavorite":"0","isFriendly":"0","isHostile":"0","tileId":"1348","xCoord":"10","yCoord":"68","tileLevel":"4","tileCityId":"233","tileUserId":"232","displayName":"Steve","race":"2","cityId":"233","cityUserId":"232","cityName":"Steves"},"a301483":{"bookmarkId":"301483","name":"Farm 010 071","isFavorite":"0","isFriendly":"0","isHostile":"0","tileId":"1371","xCoord":"10","yCoord":"71","tileLevel":"7","tileCityId":"96304","tileUserId":"250000","displayName":"Oslo","race":"2","cityId":"96304","cityUserId":"250000","cityName":"Halden"},"a301500":{"bookmarkId":"301500","name":"Farm 009 089","isFavorite":"0","isFriendly":"0","isHostile":"0","tileId":"1744","xCoord":"9","yCoord":"89","tileLevel":"7","tileCityId":"28339","tileUserId":"49360","displayName":"Wittet01","race":"2","cityId":"28339","cityUserId":"49360","cityName":"Isle of Staten"},"a301526":{"bookmarkId":"301526","name":"Farm 010 101","isFavorite":"0","isFriendly":"0","isHostile":"0","tileId":"2121","xCoord":"10","yCoord":"101","tileLevel":"4","tileCityId":"131939","tileUserId":"1806032","displayName":"Runebreaker","race":"1","cityId":"131939","cityUserId":"1806032","cityName":"Atldorf"},"a302100":{"bookmarkId":"302100","name":"Farm 007 108","isFavorite":"0","isFriendly":"0","isHostile":"0","tileId":"2133","xCoord":"7","yCoord":"108","tileLevel":"3","tileCityId":"93761","tileUserId":"242584","displayName":"Random_Hero","race":"1","cityId":"93761","cityUserId":"242584","cityName":"Goosecock"},"a302459":{"bookmarkId":"302459","name":"Farm 053 124","isFavorite":"0","isFriendly":"0","isHostile":"0","tileId":"10614","xCoord":"53","yCoord":"124","tileLevel":"4","tileCityId":"131784","tileUserId":"2427232","displayName":"EnV","race":"1","cityId":"131784","cityUserId":"2427232","cityName":"Gotham City"},"a302461":{"bookmarkId":"302461","name":"Farm 007 016","isFavorite":"0","isFriendly":"1","isHostile":"0","tileId":"181","xCoord":"7","yCoord":"16","tileLevel":"6","tileCityId":"71908","tileUserId":"174192","displayName":"kleckville","race":"1","cityId":"71908","cityUserId":"174192","cityName":"happyland"},"a303089":{"bookmarkId":"303089","name":"Farm 059 139","isFavorite":"0","isFriendly":"0","isHostile":"0","tileId":"10794","xCoord":"59","yCoord":"139","tileLevel":"4","tileCityId":"20530","tileUserId":"29368","displayName":"Gauge","race":"1","cityId":"20530","cityUserId":"29368","cityName":"Darkhall"},"a303404":{"bookmarkId":"303404","name":"Maches good","isFavorite":"0","isFriendly":"1","isHostile":"0","tileId":"1230","xCoord":"1","yCoord":"70","tileLevel":"9","tileCityId":"129637","tileUserId":"156785","displayName":"Maches","race":"2","cityId":"129637","cityUserId":"156785","cityName":"Gallifrey"},"a304884":{"bookmarkId":"304884","name":"KAcademy 528 069","isFavorite":"0","isFriendly":"0","isHostile":"0","tileId":"105339","xCoord":"528","yCoord":"69","tileLevel":"9","tileCityId":"53885","tileUserId":"119378","displayName":"Arragil","race":"1","cityId":"53885","cityUserId":"119378","cityName":"1 Castle Arra"},"a305970":{"bookmarkId":"305970","name":"Farm 020 189","isFavorite":"0","isFriendly":"0","isHostile":"0","tileId":"3949","xCoord":"20","yCoord":"189","tileLevel":"1","tileCityId":"2162","tileUserId":"2143","displayName":"solo","race":"2","cityId":"2162","cityUserId":"2143","cityName":"NewCity1NJ"},"a306245":{"bookmarkId":"306245","name":"Farm 170 229","isFavorite":"0","isFriendly":"0","isHostile":"0","tileId":"192549","xCoord":"170","yCoord":"229","tileLevel":"1","tileCityId":"136031","tileUserId":"3150980","displayName":"MrsRobinson","race":"2","cityId":"136031","cityUserId":"3150980","cityName":"TheGraduate"},"a306249":{"bookmarkId":"306249","name":"Farm 015 071","isFavorite":"0","isFriendly":"0","isHostile":"0","tileId":"1471","xCoord":"15","yCoord":"71","tileLevel":"3","tileCityId":"68880","tileUserId":"164240","displayName":"azzakurniawan69","race":"2","cityId":"68880","cityUserId":"164240","cityName":"Gatenes clork"},"a306766":{"bookmarkId":"306766","name":"Farm 159 121","isFavorite":"0","isFriendly":"0","isHostile":"0","tileId":"30716","xCoord":"159","yCoord":"121","tileLevel":"3","tileCityId":"28882","tileUserId":"51112","displayName":"RStud","race":"2","cityId":"28882","cityUserId":"51112","cityName":"NewCity13FS"},"a306771":{"bookmarkId":"306771","name":"Farm 157 106","isFavorite":"0","isFriendly":"0","isHostile":"0","tileId":"30331","xCoord":"157","yCoord":"106","tileLevel":"9","tileCityId":"89290","tileUserId":"228428","displayName":"Renhia","race":"2","cityId":"89290","cityUserId":"228428","cityName":"Kirrob"},"a306826":{"bookmarkId":"306826","name":"Farm 152 121","isFavorite":"0","isFriendly":"0","isHostile":"0","tileId":"30606","xCoord":"152","yCoord":"121","tileLevel":"5","tileCityId":"89017","tileUserId":"227568","displayName":"Zlatarien","race":"2","cityId":"89017","cityUserId":"227568","cityName":"NewCity4VLC"},"a306828":{"bookmarkId":"306828","name":"Farm 154 104","isFavorite":"0","isFriendly":"0","isHostile":"0","tileId":"30219","xCoord":"154","yCoord":"104","tileLevel":"6","tileCityId":"25202","tileUserId":"39176","displayName":"Trident","race":"1","cityId":"25202","cityUserId":"39176","cityName":"Hell"},"a306934":{"bookmarkId":"306934","name":"Farm 162 095","isFavorite":"0","isFriendly":"0","isHostile":"0","tileId":"33660","xCoord":"162","yCoord":"95","tileLevel":"5","tileCityId":"77873","tileUserId":"192224","displayName":"Scor","race":"1","cityId":"77873","cityUserId":"192224","cityName":"The Dunadain"},"a306935":{"bookmarkId":"306935","name":"Farm 155 098","isFavorite":"0","isFriendly":"0","isHostile":"0","tileId":"29898","xCoord":"155","yCoord":"98","tileLevel":"3","tileCityId":"21467","tileUserId":"30416","displayName":"DARKSABER","race":"1","cityId":"21467","cityUserId":"30416","cityName":"Throngar"},"a306963":{"bookmarkId":"306963","name":"Farm 134 073","isFavorite":"0","isFriendly":"0","isHostile":"0","tileId":"25468","xCoord":"134","yCoord":"73","tileLevel":"6","tileCityId":"136097","tileUserId":"3500288","displayName":"Firlia","race":"2","cityId":"136097","cityUserId":"3500288","cityName":"NewCity230U8"},"a306983":{"bookmarkId":"306983","name":"Farm 132 102","isFavorite":"0","isFriendly":"0","isHostile":"0","tileId":"26207","xCoord":"132","yCoord":"102","tileLevel":"1","tileCityId":"118051","tileUserId":"46192","displayName":"lannister","race":"2","cityId":"118051","cityUserId":"46192","cityName":"Lannisport"},"a306985":{"bookmarkId":"306985","name":"Farm 138 113","isFavorite":"0","isFriendly":"0","isHostile":"0","tileId":"26363","xCoord":"138","yCoord":"113","tileLevel":"7","tileCityId":"22259","tileUserId":"31328","displayName":"Lissx","race":"2","cityId":"22259","cityUserId":"31328","cityName":"29 palms"},"a306986":{"bookmarkId":"306986","name":"Farm 131 122","isFavorite":"0","isFriendly":"0","isHostile":"0","tileId":"26602","xCoord":"131","yCoord":"122","tileLevel":"8","tileCityId":"107573","tileUserId":"559800","displayName":"Alexander01","race":"2","cityId":"107573","cityUserId":"559800","cityName":"Thunderdome"},"a310518":{"bookmarkId":"310518","name":"Farm 066 068 food","isFavorite":"0","isFriendly":"0","isHostile":"0","tileId":"13328","xCoord":"66","yCoord":"68","tileLevel":"5","tileCityId":"135650","tileUserId":"117056","displayName":"Alterego","race":"1","cityId":"135650","cityUserId":"117056","cityName":"Twinkie"},"a310521":{"bookmarkId":"310521","name":"Farm 071 082 good","isFavorite":"0","isFriendly":"0","isHostile":"0","tileId":"13802","xCoord":"71","yCoord":"82","tileLevel":"9","tileCityId":"91032","tileUserId":"234404","displayName":"Mallory","race":"2","cityId":"91032","cityUserId":"234404","cityName":"NewCity50V8"},"a310542":{"bookmarkId":"310542","name":"Farm 070 153","isFavorite":"0","isFriendly":"0","isHostile":"0","tileId":"14973","xCoord":"70","yCoord":"153","tileLevel":"7","tileCityId":"91189","tileUserId":"234868","displayName":"Dannyboy","race":"1","cityId":"91189","cityUserId":"234868","cityName":"Balamorey"},"a310544":{"bookmarkId":"310544","name":"Farm 072 104 good","isFavorite":"0","isFriendly":"0","isHostile":"0","tileId":"14209","xCoord":"72","yCoord":"104","tileLevel":"9","tileCityId":"50342","tileUserId":"110875","displayName":"Gatorkid21","race":"2","cityId":"50342","cityUserId":"110875","cityName":"Nowhereville"},"a310545":{"bookmarkId":"310545","name":"Farm 065 160","isFavorite":"0","isFriendly":"0","isHostile":"0","tileId":"14900","xCoord":"65","yCoord":"160","tileLevel":"5","tileCityId":"69572","tileUserId":"166336","displayName":"x3xEx","race":"2","cityId":"69572","cityUserId":"166336","cityName":"New Castle"},"a312532":{"bookmarkId":"312532","name":"Farm 023 083","isFavorite":"0","isFriendly":"0","isHostile":"0","tileId":"5613","xCoord":"23","yCoord":"83","tileLevel":"5","tileCityId":"90827","tileUserId":"233716","displayName":"Khalisse","race":"2","cityId":"90827","cityUserId":"233716","cityName":"Septors Might"},"a313662":{"bookmarkId":"313662","name":"Farm 096 142","isFavorite":"0","isFriendly":"0","isHostile":"0","tileId":"19102","xCoord":"96","yCoord":"142","tileLevel":"4","tileCityId":"21088","tileUserId":"29392","displayName":"Redhound","race":"2","cityId":"21088","cityUserId":"29392","cityName":"Helmsdeep"},"a315712":{"bookmarkId":"315712","name":"Stony4","isFavorite":"1","isFriendly":"0","isHostile":"0","tileId":"188708","xCoord":"157","yCoord":"223","tileLevel":"10","tileCityId":"129629","tileUserId":"1550373","displayName":"Stony4","race":"2","cityId":"129629","cityUserId":"1550373","cityName":"Stony 4"},"a315954":{"bookmarkId":"315954","name":"Shadow 058 301","isFavorite":"0","isFriendly":"0","isHostile":"0","tileId":"170311","xCoord":"58","yCoord":"301","tileLevel":"9","tileCityId":"121355","tileUserId":"1546892","displayName":"Bloodguard","race":"2","cityId":"121355","cityUserId":"1546892","cityName":"Westron"},"a315965":{"bookmarkId":"315965","name":"Shadow 096 398","isFavorite":"0","isFriendly":"0","isHostile":"0","tileId":"179978","xCoord":"96","yCoord":"398","tileLevel":"9","tileCityId":"76665","tileUserId":"189260","displayName":"Londonite","race":"2","cityId":"76665","cityUserId":"189260","cityName":"Haven"},"a315968":{"bookmarkId":"315968","name":"Shadow 116 398","isFavorite":"0","isFriendly":"0","isHostile":"0","tileId":"183978","xCoord":"116","yCoord":"398","tileLevel":"9","tileCityId":"135193","tileUserId":"3222889","displayName":"spy_hunter","race":"2","cityId":"135193","cityUserId":"3222889","cityName":"Kakariko"},"a316079":{"bookmarkId":"316079","name":"Shadow 250 120","isFavorite":"0","isFriendly":"0","isHostile":"0","tileId":"50200","xCoord":"250","yCoord":"120","tileLevel":"9","tileCityId":"11996","tileUserId":"17918","displayName":"bigdaryl","race":"2","cityId":"11996","cityUserId":"17918","cityName":"big d nigga"},"a316089":{"bookmarkId":"316089","name":"Shadow 093 604","isFavorite":"0","isFriendly":"0","isHostile":"0","tileId":"496214","xCoord":"93","yCoord":"604","tileLevel":"8","tileCityId":"12311","tileUserId":"18468","displayName":"Heathervene","race":"2","cityId":"12311","cityUserId":"18468","cityName":"Heatherdale"},"a317917":{"bookmarkId":"317917","name":"Shadow 729 779","isFavorite":"0","isFriendly":"0","isHostile":"0","tileId":"627394","xCoord":"729","yCoord":"779","tileLevel":"3","tileCityId":"0","tileUserId":"0","displayName":"","race":"","cityId":"","cityUserId":"","cityName":""},"a317923":{"bookmarkId":"317923","name":"Shadow 613 763","isFavorite":"0","isFriendly":"0","isHostile":"0","tileId":"603413","xCoord":"613","yCoord":"763","tileLevel":"9","tileCityId":"129099","tileUserId":"1030865","displayName":"Maximus122","race":"2","cityId":"129099","cityUserId":"1030865","cityName":"Shelmax"},"a317925":{"bookmarkId":"317925","name":"Shadow 760 122","isFavorite":"0","isFriendly":"0","isHostile":"0","tileId":"150722","xCoord":"760","yCoord":"122","tileLevel":"9","tileCityId":"9948","tileUserId":"737","displayName":"Echo","race":"2","cityId":"9948","cityUserId":"737","cityName":"1 titis tavern"},"a317929":{"bookmarkId":"317929","name":"Shadow 772 239","isFavorite":"0","isFriendly":"0","isHostile":"0","tileId":"312684","xCoord":"772","yCoord":"239","tileLevel":"9","tileCityId":"128566","tileUserId":"1929381","displayName":"reeveland","race":"2","cityId":"128566","cityUserId":"1929381","cityName":"reeveland"},"a318048":{"bookmarkId":"318048","name":"Shadow 154 015","isFavorite":"0","isFriendly":"0","isHostile":"0","tileId":"28270","xCoord":"154","yCoord":"15","tileLevel":"9","tileCityId":"83464","tileUserId":"211592","displayName":"zoven77","race":"1","cityId":"83464","cityUserId":"211592","cityName":"zoven"},"a318051":{"bookmarkId":"318051","name":"Shadow 127 474","isFavorite":"0","isFriendly":"0","isHostile":"0","tileId":"345359","xCoord":"127","yCoord":"474","tileLevel":"1","tileCityId":"159470","tileUserId":"3908243","displayName":"sion2013","race":"1","cityId":"159470","cityUserId":"3908243","cityName":"NewCity2BRMB"},"a318193":{"bookmarkId":"318193","name":"Shadow 156 486","isFavorite":"0","isFriendly":"0","isHostile":"0","tileId":"349926","xCoord":"156","yCoord":"486","tileLevel":"9","tileCityId":"132625","tileUserId":"193723","displayName":"Hogsgonewild","race":"1","cityId":"132625","cityUserId":"193723","cityName":"WooPigSooie2"},"a318202":{"bookmarkId":"318202","name":"Shadow 721 360","isFavorite":"0","isFriendly":"0","isHostile":"0","tileId":"306880","xCoord":"721","yCoord":"360","tileLevel":"9","tileCityId":"740","tileUserId":"737","displayName":"Echo","race":"2","cityId":"740","cityUserId":"737","cityName":"Fort Echo"},"a318206":{"bookmarkId":"318206","name":"Shadow 157 487","isFavorite":"0","isFriendly":"0","isHostile":"0","tileId":"349909","xCoord":"157","yCoord":"484","tileLevel":"7","tileCityId":"0","tileUserId":"0","displayName":"","race":"","cityId":"","cityUserId":"","cityName":""},"a318207":{"bookmarkId":"318207","name":"Shadow 159 481","isFavorite":"0","isFriendly":"0","isHostile":"0","tileId":"349916","xCoord":"159","yCoord":"481","tileLevel":"9","tileCityId":"78436","tileUserId":"193723","displayName":"Hogsgonewild","race":"1","cityId":"78436","cityUserId":"193723","cityName":"WooPigSooie"},"a323940":{"bookmarkId":"323940","name":"Shadow 055 508","isFavorite":"0","isFriendly":"0","isHostile":"0","tileId":"330248","xCoord":"55","yCoord":"508","tileLevel":"9","tileCityId":"133125","tileUserId":"644606","displayName":"sarabeex","race":"2","cityId":"133125","cityUserId":"644606","cityName":"GrapeJelly"},"a323945":{"bookmarkId":"323945","name":"Shadow 596 066","isFavorite":"0","isFriendly":"0","isHostile":"0","tileId":"117526","xCoord":"596","yCoord":"66","tileLevel":"9","tileCityId":"111873","tileUserId":"580334","displayName":"Cbwrx","race":"2","cityId":"111873","cityUserId":"580334","cityName":"I own u"},"a323947":{"bookmarkId":"323947","name":"Shadow 102 702","isFavorite":"0","isFriendly":"0","isHostile":"0","tileId":"502007","xCoord":"102","yCoord":"702","tileLevel":"9","tileCityId":"123254","tileUserId":"102940","displayName":"PercyJackson","race":"2","cityId":"123254","cityUserId":"102940","cityName":"Isengard"},"a323961":{"bookmarkId":"323961","name":"Shadow 722 169","isFavorite":"0","isFriendly":"0","isHostile":"0","tileId":"147234","xCoord":"722","yCoord":"169","tileLevel":"9","tileCityId":"128946","tileUserId":"1933253","displayName":"Gamol","race":"2","cityId":"128946","cityUserId":"1933253","cityName":"Great Warrior"},"a323965":{"bookmarkId":"323965","name":"Shadow 165 500","isFavorite":"0","isFriendly":"0","isHostile":"0","tileId":"353700","xCoord":"165","yCoord":"500","tileLevel":"1","tileCityId":"159498","tileUserId":"1249140","displayName":"NewUser-QRUC","race":"1","cityId":"159498","cityUserId":"1249140","cityName":"NewCityQRUC"},"a324082":{"bookmarkId":"324082","name":"Farm 142 179","isFavorite":"0","isFriendly":"0","isHostile":"0","tileId":"31284","xCoord":"142","yCoord":"179","tileLevel":"5","tileCityId":"24518","tileUserId":"34368","displayName":"conceited","race":"2","cityId":"24518","cityUserId":"34368","cityName":"NewCityQIO"},"a324091":{"bookmarkId":"324091","name":"Farm 150 126","isFavorite":"0","isFriendly":"0","isHostile":"0","tileId":"30546","xCoord":"150","yCoord":"126","tileLevel":"2","tileCityId":"95250","tileUserId":"247052","displayName":"Shauny","race":"2","cityId":"95250","cityUserId":"247052","cityName":"NewCity5AMK"},"a328184":{"bookmarkId":"328184","name":"Bank Lord","isFavorite":"1","isFriendly":"0","isHostile":"0","tileId":"83360","xCoord":"407","yCoord":"175","tileLevel":"2","tileCityId":"158669","tileUserId":"4953162","displayName":"Lordlordlord","race":"1","cityId":"158669","cityUserId":"4953162","cityName":"NewCity2Y5VU"},"a328734":{"bookmarkId":"328734","name":"Farm 132 066","isFavorite":"0","isFriendly":"0","isHostile":"0","tileId":"25431","xCoord":"132","yCoord":"66","tileLevel":"10","tileCityId":"85766","tileUserId":"218576","displayName":"Gladale","race":"2","cityId":"85766","cityUserId":"218576","cityName":"Passion"},"a328735":{"bookmarkId":"328735","name":"Farm 156 060","isFavorite":"0","isFriendly":"0","isHostile":"0","tileId":"29180","xCoord":"156","yCoord":"60","tileLevel":"4","tileCityId":"65910","tileUserId":"156816","displayName":"SykoParslet","race":"2","cityId":"65910","cityUserId":"156816","cityName":"Galarta"},"a328736":{"bookmarkId":"328736","name":"Farm 149 066 food","isFavorite":"0","isFriendly":"0","isHostile":"0","tileId":"29341","xCoord":"149","yCoord":"66","tileLevel":"6","tileCityId":"102784","tileUserId":"267808","displayName":"Nicanic77","race":"2","cityId":"102784","cityUserId":"267808","cityName":"LunarSoul"},"a328737":{"bookmarkId":"328737","name":"Farm 146 100 good","isFavorite":"0","isFriendly":"0","isHostile":"0","tileId":"29780","xCoord":"146","yCoord":"100","tileLevel":"7","tileCityId":"7103","tileUserId":"7012","displayName":"Jeffrealm","race":"2","cityId":"7103","cityUserId":"7012","cityName":"NewCity5ES"},"a329430":{"bookmarkId":"329430","name":"Shadow 115 020","isFavorite":"0","isFriendly":"0","isHostile":"0","tileId":"24100","xCoord":"125","yCoord":"20","tileLevel":"9","tileCityId":"31734","tileUserId":"59407","displayName":"Leinhart","race":"2","cityId":"31734","cityUserId":"59407","cityName":"Ebinissia"},"a331269":{"bookmarkId":"331269","name":"Shadow 300 093","isFavorite":"0","isFriendly":"0","isHostile":"0","tileId":"57973","xCoord":"300","yCoord":"93","tileLevel":"5","tileCityId":"119433","tileUserId":"18468","displayName":"Heathervene","race":"2","cityId":"119433","cityUserId":"18468","cityName":"Heatherdene"},"a331274":{"bookmarkId":"331274","name":"Shadow 003 105","isFavorite":"0","isFriendly":"0","isHostile":"0","tileId":"2015","xCoord":"3","yCoord":"105","tileLevel":"9","tileCityId":"103027","tileUserId":"268608","displayName":"xShadeSlayerx","race":"2","cityId":"103027","cityUserId":"268608","cityName":"Uru'baen"},"a332518":{"bookmarkId":"332518","name":"Farm 195 149","isFavorite":"0","isFriendly":"0","isHostile":"0","tileId":"39049","xCoord":"195","yCoord":"149","tileLevel":"7","tileCityId":"95086","tileUserId":"246536","displayName":"Murral19","race":"2","cityId":"95086","cityUserId":"246536","cityName":"Nerrina"},"a332530":{"bookmarkId":"332530","name":"Farm 197 101","isFavorite":"0","isFriendly":"0","isHostile":"0","tileId":"38306","xCoord":"197","yCoord":"101","tileLevel":"6","tileCityId":"74352","tileUserId":"182696","displayName":"Jocke","race":"2","cityId":"74352","cityUserId":"182696","cityName":"YMCMB"},"a332552":{"bookmarkId":"332552","name":"Shadow 099 058","isFavorite":"0","isFriendly":"0","isHostile":"0","tileId":"17193","xCoord":"99","yCoord":"58","tileLevel":"9","tileCityId":"87635","tileUserId":"223288","displayName":"orangefart","race":"2","cityId":"87635","cityUserId":"223288","cityName":"Lothlorien"},"a332558":{"bookmarkId":"332558","name":"Shadow 057 050","isFavorite":"0","isFriendly":"0","isHostile":"0","tileId":"9135","xCoord":"57","yCoord":"50","tileLevel":"9","tileCityId":"119756","tileUserId":"344097","displayName":"DoVaKeen","race":"2","cityId":"119756","cityUserId":"344097","cityName":"Skyrim"},"a332567":{"bookmarkId":"332567","name":"Shadow 052 249","isFavorite":"0","isFriendly":"0","isHostile":"0","tileId":"169034","xCoord":"52","yCoord":"249","tileLevel":"5","tileCityId":"135720","tileUserId":"189868","displayName":"Spyrowd","race":"2","cityId":"135720","cityUserId":"189868","cityName":"Terror in tokyo"},"a334979":{"bookmarkId":"334979","name":"Farm 112 107","isFavorite":"0","isFriendly":"0","isHostile":"0","tileId":"22232","xCoord":"112","yCoord":"107","tileLevel":"8","tileCityId":"81368","tileUserId":"203728","displayName":"Piksi","race":"2","cityId":"81368","cityUserId":"203728","cityName":"Piksiland"},"a335799":{"bookmarkId":"335799","name":"Farm 159 165","isFavorite":"0","isFriendly":"0","isHostile":"0","tileId":"31520","xCoord":"159","yCoord":"165","tileLevel":"7","tileCityId":"27316","tileUserId":"45888","displayName":"musicmatt","race":"2","cityId":"27316","cityUserId":"45888","cityName":"NewCityZEO"},"a336004":{"bookmarkId":"336004","name":"Farm 107 003","isFavorite":"0","isFriendly":"0","isHostile":"0","tileId":"20108","xCoord":"107","yCoord":"3","tileLevel":"8","tileCityId":"43540","tileUserId":"92832","displayName":"oracle","race":"2","cityId":"43540","cityUserId":"92832","cityName":"exa"},"a338056":{"bookmarkId":"338056","name":"Farm 188 141","isFavorite":"0","isFriendly":"0","isHostile":"0","tileId":"38911","xCoord":"188","yCoord":"141","tileLevel":"7","tileCityId":"72580","tileUserId":"176640","displayName":"daniel0913","race":"2","cityId":"72580","cityUserId":"176640","cityName":"NewCity3SAO"},"a338071":{"bookmarkId":"338071","name":"Farm 194 175","isFavorite":"0","isFriendly":"0","isHostile":"0","tileId":"39470","xCoord":"194","yCoord":"175","tileLevel":"9","tileCityId":"40544","tileUserId":"84119","displayName":"OrkHunter","race":"1","cityId":"40544","cityUserId":"84119","cityName":"Dragons Heart"},"a338094":{"bookmarkId":"338094","name":"Farm 198 138","isFavorite":"0","isFriendly":"0","isHostile":"0","tileId":"38788","xCoord":"198","yCoord":"138","tileLevel":"4","tileCityId":"99264","tileUserId":"257232","displayName":"morton","race":"1","cityId":"99264","cityUserId":"257232","cityName":"mortonton"},"a338173":{"bookmarkId":"338173","name":"Farm 196 131","isFavorite":"0","isFriendly":"0","isHostile":"0","tileId":"38751","xCoord":"196","yCoord":"131","tileLevel":"4","tileCityId":"138911","tileUserId":"3874264","displayName":"LordSilver","race":"2","cityId":"138911","cityUserId":"3874264","cityName":"Silverdale"},"a338273":{"bookmarkId":"338273","name":"Farm 198 126","isFavorite":"0","isFriendly":"0","isHostile":"0","tileId":"38736","xCoord":"198","yCoord":"126","tileLevel":"6","tileCityId":"85920","tileUserId":"219024","displayName":"Joonas","race":"1","cityId":"85920","cityUserId":"219024","cityName":"Bjasur"},"a338384":{"bookmarkId":"338384","name":"Farm 199 108","isFavorite":"0","isFriendly":"0","isHostile":"0","tileId":"38343","xCoord":"199","yCoord":"108","tileLevel":"8","tileCityId":"105180","tileUserId":"275402","displayName":"Platonarchist","race":"2","cityId":"105180","cityUserId":"275402","cityName":"Bristol"},"a338441":{"bookmarkId":"338441","name":"Farm 193 097","isFavorite":"0","isFriendly":"0","isHostile":"0","tileId":"37887","xCoord":"193","yCoord":"97","tileLevel":"4","tileCityId":"39059","tileUserId":"79968","displayName":"Mike1959b","race":"1","cityId":"39059","cityUserId":"79968","cityName":"NewCity1PPC"},"a338446":{"bookmarkId":"338446","name":"Farm 199 095","isFavorite":"0","isFriendly":"0","isHostile":"0","tileId":"37970","xCoord":"199","yCoord":"95","tileLevel":"6","tileCityId":"117670","tileUserId":"84119","displayName":"OrkHunter","race":"1","cityId":"117670","cityUserId":"84119","cityName":"Dragons Heart 2"},"a338453":{"bookmarkId":"338453","name":"Farm 197 041","isFavorite":"0","isFriendly":"0","isHostile":"0","tileId":"37106","xCoord":"197","yCoord":"41","tileLevel":"4","tileCityId":"68376","tileUserId":"162888","displayName":"Bahruce","race":"2","cityId":"68376","cityUserId":"162888","cityName":"Bahruce"},"a338575":{"bookmarkId":"338575","name":"Farm 196 015 food","isFavorite":"0","isFriendly":"0","isHostile":"0","tileId":"36355","xCoord":"196","yCoord":"15","tileLevel":"5","tileCityId":"138780","tileUserId":"1610368","displayName":"Teqnik","race":"2","cityId":"138780","cityUserId":"1610368","cityName":"Bloodmoore"},"a338592":{"bookmarkId":"338592","name":"Farm 190 067","isFavorite":"0","isFriendly":"0","isHostile":"0","tileId":"37347","xCoord":"190","yCoord":"67","tileLevel":"7","tileCityId":"112185","tileUserId":"581659","displayName":"PFgrad","race":"1","cityId":"112185","cityUserId":"581659","cityName":"PFgrad"},"a338596":{"bookmarkId":"338596","name":"Farm 192 018 food","isFavorite":"0","isFriendly":"0","isHostile":"0","tileId":"36283","xCoord":"192","yCoord":"18","tileLevel":"4","tileCityId":"98600","tileUserId":"255488","displayName":"TheDutchFactory","race":"1","cityId":"98600","cityUserId":"255488","cityName":"Netherlands"},"a338608":{"bookmarkId":"338608","name":"Farm 191 006","isFavorite":"0","isFriendly":"0","isHostile":"0","tileId":"36226","xCoord":"191","yCoord":"6","tileLevel":"4","tileCityId":"85781","tileUserId":"218592","displayName":"Stoneknee","race":"1","cityId":"85781","cityUserId":"218592","cityName":"NewCity4OO0"},"a338611":{"bookmarkId":"338611","name":"Farm 186 060","isFavorite":"0","isFriendly":"0","isHostile":"0","tileId":"36980","xCoord":"186","yCoord":"60","tileLevel":"5","tileCityId":"29128","tileUserId":"51704","displayName":"Tylertarious","race":"2","cityId":"29128","cityUserId":"51704","cityName":"Tulkethabore"},"a338641":{"bookmarkId":"338641","name":"Farm 183 056","isFavorite":"0","isFriendly":"0","isHostile":"0","tileId":"36886","xCoord":"183","yCoord":"56","tileLevel":"4","tileCityId":"80207","tileUserId":"199664","displayName":"AbbeyMarjorie","race":"2","cityId":"80207","cityUserId":"199664","cityName":"Gallifrey"},"a338651":{"bookmarkId":"338651","name":"Farm 161 066","isFavorite":"0","isFriendly":"0","isHostile":"0","tileId":"33226","xCoord":"161","yCoord":"66","tileLevel":"3","tileCityId":"134427","tileUserId":"2727952","displayName":"bighands","race":"2","cityId":"134427","cityUserId":"2727952","cityName":"eatme"},"a338655":{"bookmarkId":"338655","name":"Farm 162 066 big","isFavorite":"0","isFriendly":"0","isHostile":"0","tileId":"33231","xCoord":"162","yCoord":"66","tileLevel":"9","tileCityId":"47498","tileUserId":"103569","displayName":"Nilhisiewen","race":"2","cityId":"47498","cityUserId":"103569","cityName":"Brithombar"},"a338875":{"bookmarkId":"338875","name":"Farm 092 120","isFavorite":"0","isFriendly":"0","isHostile":"0","tileId":"18285","xCoord":"92","yCoord":"120","tileLevel":"6","tileCityId":"138936","tileUserId":"3874304","displayName":"Li57","race":"2","cityId":"138936","cityUserId":"3874304","cityName":"Li57"},"a338890":{"bookmarkId":"338890","name":"Farm 093 053","isFavorite":"0","isFriendly":"0","isHostile":"0","tileId":"17063","xCoord":"93","yCoord":"53","tileLevel":"5","tileCityId":"95687","tileUserId":"248376","displayName":"TurnAround","race":"2","cityId":"95687","cityUserId":"248376","cityName":"NewCity5BNC"},"a338984":{"bookmarkId":"338984","name":"Farm 095 111","isFavorite":"0","isFriendly":"0","isHostile":"0","tileId":"18271","xCoord":"95","yCoord":"111","tileLevel":"5","tileCityId":"85597","tileUserId":"218056","displayName":"mkulifay13","race":"2","cityId":"85597","cityUserId":"218056","cityName":"NewCity4O94"},"a339002":{"bookmarkId":"339002","name":"Farm 097 145","isFavorite":"0","isFriendly":"0","isHostile":"0","tileId":"19110","xCoord":"97","yCoord":"145","tileLevel":"7","tileCityId":"21552","tileUserId":"30512","displayName":"Lou","race":"1","cityId":"21552","cityUserId":"30512","cityName":"Louburg"},"a339123":{"bookmarkId":"339123","name":"Farm 101 126","isFavorite":"0","isFriendly":"0","isHostile":"0","tileId":"22426","xCoord":"101","yCoord":"126","tileLevel":"5","tileCityId":"88489","tileUserId":"225904","displayName":"Morigul","race":"2","cityId":"88489","cityUserId":"225904","cityName":"Ered Luin"},"a339193":{"bookmarkId":"339193","name":"Farm 106 150","isFavorite":"0","isFriendly":"0","isHostile":"0","tileId":"22930","xCoord":"106","yCoord":"150","tileLevel":"4","tileCityId":"16902","tileUserId":"25200","displayName":"KingJones","race":"2","cityId":"16902","cityUserId":"25200","cityName":"Helm's Deep"},"a339242":{"bookmarkId":"339242","name":"Farm 111 149","isFavorite":"0","isFriendly":"0","isHostile":"0","tileId":"23029","xCoord":"111","yCoord":"149","tileLevel":"5","tileCityId":"6032","tileUserId":"5960","displayName":"Thorkel","race":"2","cityId":"6032","cityUserId":"5960","cityName":"Gil'Doren"},"a339243":{"bookmarkId":"339243","name":"Farm 113 145","isFavorite":"0","isFriendly":"0","isHostile":"0","tileId":"23015","xCoord":"113","yCoord":"145","tileLevel":"4","tileCityId":"77048","tileUserId":"190176","displayName":"Sigurd","race":"2","cityId":"77048","cityUserId":"190176","cityName":"Ziost"},"a339246":{"bookmarkId":"339246","name":"Farm 111 250","isFavorite":"0","isFriendly":"0","isHostile":"0","tileId":"181030","xCoord":"111","yCoord":"250","tileLevel":"4","tileCityId":"90210","tileUserId":"231709","displayName":"Trevor483","race":"2","cityId":"90210","cityUserId":"231709","cityName":"Magnum X"},"a339248":{"bookmarkId":"339248","name":"Farm 112 249","isFavorite":"0","isFriendly":"0","isHostile":"0","tileId":"181034","xCoord":"112","yCoord":"249","tileLevel":"6","tileCityId":"134068","tileUserId":"2938420","displayName":"TomWhiting","race":"1","cityId":"134068","cityUserId":"2938420","cityName":"Getafe my City"},"a339301":{"bookmarkId":"339301","name":"Farm 116 116","isFavorite":"0","isFriendly":"0","isHostile":"0","tileId":"22376","xCoord":"116","yCoord":"116","tileLevel":"5","tileCityId":"142161","tileUserId":"4122912","displayName":"jaikie","race":"2","cityId":"142161","cityUserId":"4122912","cityName":"Johnopopolous"},"a339302":{"bookmarkId":"339302","name":"Farm 117 116","isFavorite":"0","isFriendly":"0","isHostile":"0","tileId":"22381","xCoord":"117","yCoord":"116","tileLevel":"5","tileCityId":"25160","tileUserId":"38976","displayName":"Archrune","race":"2","cityId":"25160","cityUserId":"38976","cityName":"Archcity"},"a339304":{"bookmarkId":"339304","name":"Farm 114 073 food","isFavorite":"0","isFriendly":"1","isHostile":"0","tileId":"21468","xCoord":"114","yCoord":"73","tileLevel":"5","tileCityId":"135787","tileUserId":"3398544","displayName":"Camper9","race":"2","cityId":"135787","cityUserId":"3398544","cityName":"Camper9'sCity1"},"a339307":{"bookmarkId":"339307","name":"Farm 114 075","isFavorite":"0","isFriendly":"0","isHostile":"0","tileId":"21470","xCoord":"114","yCoord":"75","tileLevel":"7","tileCityId":"22446","tileUserId":"31544","displayName":"Shay2013","race":"1","cityId":"22446","cityUserId":"31544","cityName":"The Shire"},"a339332":{"bookmarkId":"339332","name":"Farm 117 242","isFavorite":"0","isFriendly":"0","isHostile":"0","tileId":"181107","xCoord":"117","yCoord":"242","tileLevel":"6","tileCityId":"2960","tileUserId":"2925","displayName":"limey","race":"2","cityId":"2960","cityUserId":"2925","cityName":"Millom"},"a339345":{"bookmarkId":"339345","name":"Farm 121 119","isFavorite":"0","isFriendly":"0","isHostile":"0","tileId":"26079","xCoord":"121","yCoord":"119","tileLevel":"4","tileCityId":"43451","tileUserId":"92304","displayName":"kingbum","race":"1","cityId":"43451","cityUserId":"92304","cityName":"bumgrumer"},"a339788":{"bookmarkId":"339788","name":"Farm 098 069","isFavorite":"0","isFriendly":"0","isHostile":"0","tileId":"17539","xCoord":"98","yCoord":"69","tileLevel":"6","tileCityId":"18575","tileUserId":"27168","displayName":"Dragonscale","race":"2","cityId":"18575","cityUserId":"27168","cityName":"Alpine shire"},"a341263":{"bookmarkId":"341263","name":"Farm 125 113 food","isFavorite":"0","isFriendly":"0","isHostile":"0","tileId":"26073","xCoord":"125","yCoord":"113","tileLevel":"6","tileCityId":"92570","tileUserId":"238796","displayName":"Sambarnes94","race":"2","cityId":"92570","cityUserId":"238796","cityName":"NewCity5498"},"a341265":{"bookmarkId":"341265","name":"Farm 124 150","isFavorite":"0","isFriendly":"0","isHostile":"0","tileId":"26845","xCoord":"124","yCoord":"150","tileLevel":"4","tileCityId":"16510","tileUserId":"24728","displayName":"nicholasmaximus","race":"2","cityId":"16510","cityUserId":"24728","cityName":"home"},"a341267":{"bookmarkId":"341267","name":"Farm 126 159","isFavorite":"0","isFriendly":"0","isHostile":"0","tileId":"26979","xCoord":"126","yCoord":"159","tileLevel":"5","tileCityId":"106915","tileUserId":"29088","displayName":"GingerHugz","race":"1","cityId":"106915","cityUserId":"29088","cityName":"Gingerville"},"a341274":{"bookmarkId":"341274","name":"Farm 127 160","isFavorite":"0","isFriendly":"0","isHostile":"0","tileId":"26985","xCoord":"127","yCoord":"160","tileLevel":"6","tileCityId":"20271","tileUserId":"29088","displayName":"GingerHugz","race":"1","cityId":"20271","cityUserId":"29088","cityName":"Gingerburg"},"a341281":{"bookmarkId":"341281","name":"Farm 128 250","isFavorite":"0","isFriendly":"0","isHostile":"0","tileId":"184940","xCoord":"128","yCoord":"250","tileLevel":"4","tileCityId":"55895","tileUserId":"126260","displayName":"Rankin","race":"1","cityId":"55895","cityUserId":"126260","cityName":"NewCity2PF8"},"a341657":{"bookmarkId":"341657","name":"Farm 133 069 food","isFavorite":"0","isFriendly":"0","isHostile":"0","tileId":"25439","xCoord":"133","yCoord":"69","tileLevel":"9","tileCityId":"82788","tileUserId":"208991","displayName":"smartyy","race":"2","cityId":"82788","cityUserId":"208991","cityName":"Mordor"},"a341658":{"bookmarkId":"341658","name":"Farm 136 153 good","isFavorite":"0","isFriendly":"1","isHostile":"0","tileId":"27153","xCoord":"136","yCoord":"153","tileLevel":"6","tileCityId":"138286","tileUserId":"3859856","displayName":"Rolando","race":"2","cityId":"138286","cityUserId":"3859856","cityName":"RoLand"},"a341660":{"bookmarkId":"341660","name":"Farm 134 050 good","isFavorite":"0","isFriendly":"1","isHostile":"0","tileId":"25045","xCoord":"134","yCoord":"50","tileLevel":"5","tileCityId":"134329","tileUserId":"3046256","displayName":"Reb","race":"1","cityId":"134329","cityUserId":"3046256","cityName":"Haven"},"a341676":{"bookmarkId":"341676","name":"Farm 144 130","isFavorite":"0","isFriendly":"0","isHostile":"0","tileId":"30445","xCoord":"144","yCoord":"130","tileLevel":"3","tileCityId":"132649","tileUserId":"2620088","displayName":"NewUser-1K5O8","race":"2","cityId":"132649","cityUserId":"2620088","cityName":"NewCity1K5O8"},"a341677":{"bookmarkId":"341677","name":"Farm 087 114 good","isFavorite":"0","isFriendly":"0","isHostile":"0","tileId":"18159","xCoord":"87","yCoord":"114","tileLevel":"9","tileCityId":"59821","tileUserId":"138591","displayName":"Talandrius","race":"2","cityId":"59821","cityUserId":"138591","cityName":"Talandrius"},"a341679":{"bookmarkId":"341679","name":"Farm 086 115 food","isFavorite":"0","isFriendly":"1","isHostile":"0","tileId":"18155","xCoord":"86","yCoord":"115","tileLevel":"6","tileCityId":"82297","tileUserId":"207024","displayName":"Krawn","race":"2","cityId":"82297","cityUserId":"207024","cityName":"Krawns Height"},"a344208":{"bookmarkId":"344208","name":"Farm 154 043","isFavorite":"0","isFriendly":"0","isHostile":"0","tileId":"29018","xCoord":"154","yCoord":"43","tileLevel":"7","tileCityId":"85923","tileUserId":"219028","displayName":"Bellheir","race":"2","cityId":"85923","cityUserId":"219028","cityName":"Earth Bell"},"a344268":{"bookmarkId":"344268","name":"Farm 002 028 food","isFavorite":"0","isFriendly":"0","isHostile":"0","tileId":"433","xCoord":"2","yCoord":"28","tileLevel":"9","tileCityId":"65745","tileUserId":"156427","displayName":"Cheffie","race":"1","cityId":"65745","cityUserId":"156427","cityName":"NewCity3CP7"},"a344269":{"bookmarkId":"344269","name":"Farm 048 350","isFavorite":"0","isFriendly":"0","isHostile":"0","tileId":"170940","xCoord":"48","yCoord":"350","tileLevel":"3","tileCityId":"131700","tileUserId":"855889","displayName":"Tyreon","race":"1","cityId":"131700","cityUserId":"855889","cityName":"Ironforge"},"a344272":{"bookmarkId":"344272","name":"Farm 075 012","isFavorite":"0","isFriendly":"0","isHostile":"0","tileId":"12272","xCoord":"75","yCoord":"12","tileLevel":"6","tileCityId":"48451","tileUserId":"106080","displayName":"llamallama","race":"2","cityId":"48451","cityUserId":"106080","cityName":"llamallama"},"a344275":{"bookmarkId":"344275","name":"Farm 033 032","isFavorite":"0","isFriendly":"0","isHostile":"0","tileId":"4662","xCoord":"33","yCoord":"32","tileLevel":"8","tileCityId":"75618","tileUserId":"186544","displayName":"oriktheslayer","race":"1","cityId":"75618","cityUserId":"186544","cityName":"Boonanza"},"a344290":{"bookmarkId":"344290","name":"Farm 206 104","isFavorite":"0","isFriendly":"0","isHostile":"0","tileId":"42104","xCoord":"206","yCoord":"104","tileLevel":"7","tileCityId":"88312","tileUserId":"225333","displayName":"kaybo","race":"2","cityId":"88312","cityUserId":"225333","cityName":"Lifer"},"a345110":{"bookmarkId":"345110","name":"Shadow 003 104","isFavorite":"0","isFriendly":"0","isHostile":"0","tileId":"2014","xCoord":"3","yCoord":"104","tileLevel":"8","tileCityId":"155973","tileUserId":"4831318","displayName":"EliteKushKiller","race":"1","cityId":"155973","cityUserId":"4831318","cityName":"Moria Mine"},"a355514":{"bookmarkId":"355514","name":"Farm 055 170","isFavorite":"0","isFriendly":"0","isHostile":"0","tileId":"11450","xCoord":"55","yCoord":"170","tileLevel":"6","tileCityId":"135219","tileUserId":"3242288","displayName":"wolfger","race":"2","cityId":"135219","cityUserId":"3242288","cityName":"wolfger"},"a355516":{"bookmarkId":"355516","name":"Farm 056 156","isFavorite":"0","isFriendly":"0","isHostile":"0","tileId":"11176","xCoord":"56","yCoord":"156","tileLevel":"5","tileCityId":"128130","tileUserId":"1924832","displayName":"Toblaki","race":"1","cityId":"128130","cityUserId":"1924832","cityName":"Malaz"},"a355990":{"bookmarkId":"355990","name":"Farm 002 127","isFavorite":"0","isFriendly":"0","isHostile":"0","tileId":"2432","xCoord":"2","yCoord":"127","tileLevel":"7","tileCityId":"56796","tileUserId":"129136","displayName":"Raulas","race":"2","cityId":"56796","cityUserId":"129136","cityName":"Tugasville"},"a356002":{"bookmarkId":"356002","name":"Farm 011 105","isFavorite":"0","isFriendly":"0","isHostile":"0","tileId":"2205","xCoord":"11","yCoord":"105","tileLevel":"8","tileCityId":"153","tileUserId":"152","displayName":"Frodon","race":"2","cityId":"153","cityUserId":"152","cityName":"Hobbitville"},"a356026":{"bookmarkId":"356026","name":"Farm 012 139","isFavorite":"0","isFriendly":"0","isHostile":"0","tileId":"2684","xCoord":"12","yCoord":"139","tileLevel":"5","tileCityId":"43642","tileUserId":"92980","displayName":"Everlast","race":"2","cityId":"43642","cityUserId":"92980","cityName":"Forlindon"},"a356031":{"bookmarkId":"356031","name":"Farm 013 108","isFavorite":"0","isFriendly":"0","isHostile":"0","tileId":"2238","xCoord":"13","yCoord":"108","tileLevel":"5","tileCityId":"74730","tileUserId":"183936","displayName":"Mordor12345678","race":"1","cityId":"74730","cityUserId":"183936","cityName":"Mines of Moria"},"a356034":{"bookmarkId":"356034","name":"Farm 016 109 food","isFavorite":"0","isFriendly":"0","isHostile":"0","tileId":"2329","xCoord":"16","yCoord":"109","tileLevel":"7","tileCityId":"83643","tileUserId":"212144","displayName":"Rivers","race":"2","cityId":"83643","cityUserId":"212144","cityName":"Leaves"},"a356041":{"bookmarkId":"356041","name":"Farm 017 117","isFavorite":"0","isFriendly":"0","isHostile":"0","tileId":"2382","xCoord":"17","yCoord":"117","tileLevel":"4","tileCityId":"159203","tileUserId":"5056867","displayName":"Voldermort","race":"2","cityId":"159203","cityUserId":"5056867","cityName":"Hogwarts"},"a356042":{"bookmarkId":"356042","name":"Farm 018 142","isFavorite":"0","isFriendly":"0","isHostile":"0","tileId":"3112","xCoord":"18","yCoord":"142","tileLevel":"6","tileCityId":"92338","tileUserId":"238200","displayName":"slippy100","race":"2","cityId":"92338","cityUserId":"238200","cityName":"NewCity53SO"},"a356052":{"bookmarkId":"356052","name":"Farm 026 100","isFavorite":"0","isFriendly":"0","isHostile":"0","tileId":"5780","xCoord":"26","yCoord":"100","tileLevel":"5","tileCityId":"57227","tileUserId":"130608","displayName":"Hansken","race":"2","cityId":"57227","cityUserId":"130608","cityName":"NewCity2SS0"},"a356053":{"bookmarkId":"356053","name":"Farm 026 148","isFavorite":"0","isFriendly":"0","isHostile":"0","tileId":"6928","xCoord":"26","yCoord":"148","tileLevel":"5","tileCityId":"18866","tileUserId":"27504","displayName":"Turnblom79","race":"2","cityId":"18866","cityUserId":"27504","cityName":"Turnville"},"a356084":{"bookmarkId":"356084","name":"Farm 027 137","isFavorite":"0","isFriendly":"0","isHostile":"0","tileId":"6582","xCoord":"27","yCoord":"137","tileLevel":"5","tileCityId":"109542","tileUserId":"569160","displayName":"Cleusnaar","race":"1","cityId":"109542","cityUserId":"569160","cityName":"NewCityC760"},"a356097":{"bookmarkId":"356097","name":"Farm 029 264","isFavorite":"0","isFriendly":"0","isHostile":"0","tileId":"165319","xCoord":"29","yCoord":"264","tileLevel":"5","tileCityId":"110629","tileUserId":"575002","displayName":"laourde","race":"2","cityId":"110629","cityUserId":"575002","cityName":"NewCityCBOA"},"a356098":{"bookmarkId":"356098","name":"Farm 030 141","isFavorite":"0","isFriendly":"0","isHostile":"0","tileId":"6921","xCoord":"30","yCoord":"141","tileLevel":"5","tileCityId":"67191","tileUserId":"159840","displayName":"thekightkiller","race":"2","cityId":"67191","cityUserId":"159840","cityName":"hope"},"a356112":{"bookmarkId":"356112","name":"Farm 036 154","isFavorite":"0","isFriendly":"0","isHostile":"0","tileId":"7154","xCoord":"36","yCoord":"154","tileLevel":"7","tileCityId":"66590","tileUserId":"158468","displayName":"sofaKinglow","race":"2","cityId":"66590","cityUserId":"158468","cityName":"newcity"},"a356114":{"bookmarkId":"356114","name":"Farm 037 143","isFavorite":"0","isFriendly":"0","isHostile":"0","tileId":"7108","xCoord":"37","yCoord":"143","tileLevel":"4","tileCityId":"97219","tileUserId":"252393","displayName":"Iron_Man8","race":"1","cityId":"97219","cityUserId":"252393","cityName":"Iron_kingdom8"},"a356136":{"bookmarkId":"356136","name":"Farm 046 075 good","isFavorite":"0","isFriendly":"1","isHostile":"0","tileId":"9355","xCoord":"46","yCoord":"75","tileLevel":"5","tileCityId":"52949","tileUserId":"116864","displayName":"Campoopen","race":"1","cityId":"52949","cityUserId":"116864","cityName":"NewCity2I68"},"a356139":{"bookmarkId":"356139","name":"Farm 053 135","isFavorite":"0","isFriendly":"0","isHostile":"0","tileId":"10665","xCoord":"53","yCoord":"135","tileLevel":"8","tileCityId":"137639","tileUserId":"3469310","displayName":"landergander","race":"1","cityId":"137639","cityUserId":"3469310","cityName":"u attack u die"},"a356239":{"bookmarkId":"356239","name":"Farm 062 038","isFavorite":"0","isFriendly":"0","isHostile":"0","tileId":"12483","xCoord":"62","yCoord":"38","tileLevel":"5","tileCityId":"14064","tileUserId":"21344","displayName":"Rufus1868","race":"2","cityId":"14064","cityUserId":"21344","cityName":"NewCityGGW"},"a356243":{"bookmarkId":"356243","name":"Farm 063 126","isFavorite":"0","isFriendly":"0","isHostile":"0","tileId":"14436","xCoord":"63","yCoord":"126","tileLevel":"4","tileCityId":"449","tileUserId":"448","displayName":"Lando","race":"2","cityId":"449","cityUserId":"448","cityName":"Brunswick"},"a356305":{"bookmarkId":"356305","name":"Farm 067 203","isFavorite":"0","isFriendly":"0","isHostile":"0","tileId":"172108","xCoord":"67","yCoord":"203","tileLevel":"6","tileCityId":"48485","tileUserId":"106124","displayName":"Tavi","race":"2","cityId":"48485","cityUserId":"106124","cityName":"NewCity29VW"},"a356313":{"bookmarkId":"356313","name":"Farm 067 063","isFavorite":"0","isFriendly":"0","isHostile":"0","tileId":"13308","xCoord":"67","yCoord":"63","tileLevel":"5","tileCityId":"8139","tileUserId":"8794","displayName":"Woodlandkeep","race":"2","cityId":"8139","cityUserId":"8794","cityName":"Forgotten Realm"},"a356315":{"bookmarkId":"356315","name":"Farm 069 106","isFavorite":"0","isFriendly":"0","isHostile":"0","tileId":"14141","xCoord":"69","yCoord":"106","tileLevel":"6","tileCityId":"101681","tileUserId":"264304","displayName":"Stwilt","race":"2","cityId":"101681","cityUserId":"264304","cityName":"NewCity5NXS"},"a356459":{"bookmarkId":"356459","name":"Farm 070 067 food","isFavorite":"0","isFriendly":"1","isHostile":"0","tileId":"13347","xCoord":"70","yCoord":"67","tileLevel":"5","tileCityId":"120406","tileUserId":"1528606","displayName":"me_gusta","race":"2","cityId":"120406","cityUserId":"1528606","cityName":"Mount Doom"},"a356462":{"bookmarkId":"356462","name":"Farm 070 185","isFavorite":"0","isFriendly":"0","isHostile":"0","tileId":"15725","xCoord":"70","yCoord":"185","tileLevel":"6","tileCityId":"16099","tileUserId":"24208","displayName":"Mahreo","race":"2","cityId":"16099","cityUserId":"24208","cityName":"Moldavia"},"a356465":{"bookmarkId":"356465","name":"Farm 071 023","isFavorite":"0","isFriendly":"0","isHostile":"0","tileId":"12603","xCoord":"71","yCoord":"23","tileLevel":"4","tileCityId":"113838","tileUserId":"796632","displayName":"McWade","race":"1","cityId":"113838","cityUserId":"796632","cityName":"NewCityH2OO"}}