{"allMailCount":"527","allReportCount":9620,"allianceDiplomacies":{"friendly":{"a986":{"allianceId":"986","founderUserId":"40568","allianceName":"Blood Brothers","relation":"1","membersCount":"93","rank":46,"might":"99351735","founderUserName":"Mully"},"a435":{"allianceId":"435","founderUserId":"4005","allianceName":"Canadian Shire","relation":"1","membersCount":"51","rank":66,"might":"68374457","founderUserName":"DARKWINGDUCK"},"a1500":{"allianceId":"1500","founderUserId":"68190","allianceName":"Catalunya","relation":"1","membersCount":"40","rank":68,"might":"66649845","founderUserName":"Drac"},"a2479":{"allianceId":"2479","founderUserId":"54943","allianceName":"Creatures","relation":"1","membersCount":"61","rank":26,"might":"187279533","founderUserName":"Your_Dawg"},"a103":{"allianceId":"103","founderUserId":"901","allianceName":"Dark Riders","relation":"1","membersCount":"20","rank":104,"might":"18322598","founderUserName":"Tathar"},"a343":{"allianceId":"343","founderUserId":"4158","allianceName":"Dwarf Warriors","relation":"1","membersCount":"78","rank":18,"might":"219233285","founderUserName":"GandoIf"},"a802":{"allianceId":"802","founderUserId":"25656","allianceName":"Fetch you a Box","relation":"1","membersCount":"28","rank":130,"might":"10007676","founderUserName":"pink"},"a930":{"allianceId":"930","founderUserId":"27836","allianceName":"Ghost Dragons","relation":"1","membersCount":"77","rank":41,"might":"124066896","founderUserName":"Thor512"},"a13441":{"allianceId":"13441","founderUserId":"211592","allianceName":"Grendels Brood","relation":"1","membersCount":"19","rank":null,"might":null,"founderUserName":"zoven77"},"a1989":{"allianceId":"1989","founderUserId":"108276","allianceName":"Imperium","relation":"1","membersCount":"88","rank":57,"might":"78055513","founderUserName":"Apocalypse"},"a7856":{"allianceId":"7856","founderUserId":"279117","allianceName":"Inactive Farm","relation":"1","membersCount":"1","rank":2523,"might":"5525","founderUserName":"YY_FAKIE"},"a10503":{"allianceId":"10503","founderUserId":"47387","allianceName":"Just Me","relation":"1","membersCount":"1","rank":5559,"might":"0","founderUserName":"Smudge_KOR"},"a9340":{"allianceId":"9340","founderUserId":"1544227","allianceName":"Legion of Elves","relation":"1","membersCount":"1","rank":6070,"might":"0","founderUserName":"bigfoot"},"a68":{"allianceId":"68","founderUserId":"639","allianceName":"Lords of Endore","relation":"1","membersCount":"52","rank":22,"might":"198462757","founderUserName":"Adamas"},"a11727":{"allianceId":"11727","founderUserId":"1829088","allianceName":"Magical elves","relation":"1","membersCount":"2","rank":2192,"might":"9303","founderUserName":"BillyBaggins"},"a12115":{"allianceId":"12115","founderUserId":"4178975","allianceName":"MetaI Men","relation":"1","membersCount":"39","rank":95,"might":"22567541","founderUserName":"PrincessB"},"a5737":{"allianceId":"5737","founderUserId":"123097","allianceName":"Northern Empire","relation":"1","membersCount":"85","rank":29,"might":"149634616","founderUserName":"Eylanin"},"a1865":{"allianceId":"1865","founderUserId":"21002","allianceName":"Pyro Hobbits","relation":"1","membersCount":"86","rank":99,"might":"21024403","founderUserName":"Pimp"},"a3632":{"allianceId":"3632","founderUserId":"186770","allianceName":"rehelm pact","relation":"1","membersCount":"3","rank":564,"might":"487598","founderUserName":"barlinthewise"},"a1185":{"allianceId":"1185","founderUserId":"57907","allianceName":"RidersoftheMark","relation":"1","membersCount":"89","rank":73,"might":"55598623","founderUserName":"Origen"},"a934":{"allianceId":"934","founderUserId":"1989","allianceName":"Second age","relation":"1","membersCount":"37","rank":189,"might":"4919272","founderUserName":"StonedOne"},"a7964":{"allianceId":"7964","founderUserId":"81193","allianceName":"Shadowstone","relation":"1","membersCount":"48","rank":24,"might":"190596080","founderUserName":"_Methuselah_"},"a7881":{"allianceId":"7881","founderUserId":"1586168","allianceName":"Strongbrethren","relation":"1","membersCount":"24","rank":156,"might":"7102174","founderUserName":"Yenksilver"},"a7132":{"allianceId":"7132","founderUserId":"264572","allianceName":"The Badgers","relation":"1","membersCount":"3","rank":1128,"might":"105484","founderUserName":"TheHoneyBadger"},"a1111":{"allianceId":"1111","founderUserId":"6023","allianceName":"The Watch","relation":"1","membersCount":"14","rank":460,"might":"766228","founderUserName":"xMcROYALx"},"a3629":{"allianceId":"3629","founderUserId":"135630","allianceName":"THUNDERSTRUCK","relation":"1","membersCount":"82","rank":13,"might":"269682103","founderUserName":"SanAngelo"},"a25":{"allianceId":"25","founderUserId":"153","allianceName":"TombStone","relation":"1","membersCount":"5","rank":486,"might":"669475","founderUserName":"LordWainwright"},"a10494":{"allianceId":"10494","founderUserId":"596234","allianceName":"UrFkd","relation":"1","membersCount":"1","rank":6426,"might":"0","founderUserName":"UrSCR3W3D"},"a7154":{"allianceId":"7154","founderUserId":"29944","allianceName":"Whiskers","relation":"1","membersCount":"47","rank":74,"might":"55386346","founderUserName":"Cason"}},"hostile":{"a12736":{"allianceId":"12736","founderUserId":"3286599","allianceName":"FoxFox","relation":"2","membersCount":"1","rank":2004,"might":"14321","founderUserName":"FoxFox"},"a995":{"allianceId":"995","founderUserId":"30292","allianceName":"HelemansArmy","relation":"2","membersCount":"20","rank":164,"might":"6215007","founderUserName":"Rivendale1920"},"a9809":{"allianceId":"9809","founderUserId":"1541","allianceName":"InsidiousUnited","relation":"2","membersCount":"60","rank":19,"might":"215348936","founderUserName":"phrenikos"},"a8049":{"allianceId":"8049","founderUserId":"107852","allianceName":"RivendalleElves","relation":"2","membersCount":"8","rank":1358,"might":"62353","founderUserName":"Zanebob"},"a8953":{"allianceId":"8953","founderUserId":"19422","allianceName":"The Hated","relation":"2","membersCount":"1","rank":1428,"might":"52618","founderUserName":"DarkHunters"},"a9176":{"allianceId":"9176","founderUserId":"147898","allianceName":"Whippity whip","relation":"2","membersCount":"1","rank":1673,"might":"29778","founderUserName":"Vipertown"}},"friendlyToThem":{"a325":{"allianceId":"325","founderUserId":"4831","allianceName":"THE WARRIORS","relation":"1","membersCount":"1","rank":4489,"might":"389","founderUserName":"Warriorpower"}},"friendlyToYou":{"a9758":{"allianceId":"9758","founderUserId":"1763591","allianceName":"AldmeriDominion","relation":"1","membersCount":"4","might":1125,"founderUserName":"TheWarden"},"a7264":{"allianceId":"7264","founderUserId":"279148","allianceName":"AllianceOfBruce","relation":"1","membersCount":"1","might":2483,"founderUserName":"Kirton"},"a1005":{"allianceId":"1005","founderUserId":"45475","allianceName":"DeathRow","relation":"1","membersCount":"25","might":115,"founderUserName":"RogueAura"},"a10683":{"allianceId":"10683","founderUserId":"2469984","allianceName":"Ghost Army","relation":"1","membersCount":"13","might":479,"founderUserName":"hobo5677"},"a9038":{"allianceId":"9038","founderUserId":"27402","allianceName":"MAGNUS","relation":"1","membersCount":"11","might":283,"founderUserName":"Holty93"},"a8345":{"allianceId":"8345","founderUserId":"421","allianceName":"TheNightsWatch","relation":"1","membersCount":"58","might":80,"founderUserName":"Kellen"}},"allianceId":"1018","allianceName":"Comrade in arms"},"artifactSets":{"inventory":[]},"artifacts":{"20221":"0","20323":"0","20415":"0"},"blueLight":{"max":1600,"cur":746,"level":5},"broadcast":"0","buyUpgradeRate":"0.00022","city_unit_count":{"c126934":{"u1":0,"u2":"6996","u4":"553218","u5":"548438","u6":"601364","u7":"123312","u8":"112839","u9":0,"u10":"28100","u11":"83345","u12":"25450","u13":"23700","u14":0,"u15":0,"u16":0},"c135164":{"u1":0,"u2":"3647","u4":"500","u5":0,"u6":"500","u7":0,"u8":0,"u9":0,"u10":0,"u11":"500","u12":"2700","u13":"500","u14":0,"u15":0,"u16":0}},"config":{"allianceHelp":true},"cur_time":"2013-03-04 12:20:46","dataVersion":"1","fortifications":{"city126934":{"fort52":"0","fort53":"0","fort54":"0","fort55":"0","fort56":"0","fort57":"0","fort58":"0","fort59":"0","fort60":"0"},"city135164":{"fort52":"0","fort53":"2","fort54":"2","fort55":"2","fort56":"2","fort57":"0","fort58":"0","fort59":"0","fort60":"0"}},"foundArtifacts":{"126934":false,"135164":false},"hasNewReceiveMail":false,"hasNewReport":false,"hasNewSentMail":false,"hasNewSysMail":false,"newAllInboxCount":null,"newDisasterReportCount":"0","newMailCount":"0","newReportCount":0,"newSentMailCount":0,"newTradeReports":0,"newitems":{"i1":"108","i2":"116","i3":"47","i4":"11","i5":"5","i9":"8","i69":"2","i101":"4","i102":"4","i111":"8","i112":"2","i121":"14","i131":"10","i141":"10","i142":"2","i261":"14","i262":"7","i271":"19","i272":"5","i355":"4","i361":"21","i362":"19","i363":"20","i401":"8","i599":"82","i901":"1","i911":"10","i922":"1","i923":"6","i1001":"11","i1002":"3","i1003":"4","i1004":"5","i1005":"14","i1011":"8","i1012":"6","i1013":"4","i1014":"14","i1015":"29","i1016":"1","i1021":"3","i1022":"2","i1023":"3","i1024":"6","i1025":"15","i1031":"2","i1032":"2","i1033":"3","i1034":"5","i1035":"12","i1041":"2","i1042":"2","i1043":"2","i1044":"13","i1045":"20","i1047":"2","i1202":"1","i10009":"2","i10020":"1","i10030":"1","i10031":"1","i10032":"1","i10033":"1","i10034":"1","i20221":"4","i20323":"4","i20415":"23","i50020":"2","i50050":"1","i50060":"3","i50062":"5","i60001":"2","i60010":"1","i60017":"15","i60018":"1","i60019":"4","i60023":"1","i60024":"1","i60031":"2","i60033":"1","i60035":"3","i60039":"4","i60041":"1","i60044":"6","i60048":"2","i60050":"10"},"ok":true,"player":{"datejoinUnixTime":"1355071835","truceExpireUnixTime":"0","beginproExpireUnixTime":"1355676635","fteFinishUnixTime":"1355098713","userId":"1911696","displayName":"Leith","email":"","fbuid":"0","mobileid":"b1d5ae74028aa35fb1988d3748d69f3d","playerSex":"M","usertype":"201","race":"2","status":"1","dateJoined":"2012-12-09 16:50:35","lastLogin":"2013-03-04 12:11:32","fte_finish_time":"2012-12-10 00:18:33","warStatus":"1","allianceId":"1018","might":13866984,"xp":"847290","title":"53","truceExpireTimestamp":"0000-00-00 00:00:00","beginproExpireTimestamp":"2012-12-16 16:50:35","fogExpireTimestamp":"0000-00-00 00:00:00","cnt_newmsg":"0","cnt_friendreq":"0","cnt_logins":"0","cnt_passreset":"0","cnt_connections":"0","avatarId":"0","photo_host":"0","photo_dir":"0","photo_subdir":"0","photo_name":"0","playerCityLock":"0","officerType":"3"},"players":[],"queue_atkinc":[],"reqmicrotime":1362399646.6834,"resmicrotime":1362399646.7933,"runtime":0.11420297622681,"serverSetting":{"allowJumpAllianceFromInvitation":0},"shopUpgraded":false,"strVersion":"1","timezone":"UTC","updateMarch":[],"updateMight":13866984,"updateSeed":{"ok":false,"city":{"126934":{"production":{"ok":true,"mightInc":0,"reports":[],"paid":false,"fiscalUnixTime":1362399303,"happiness":"97","grievance":"0","population":"34920","laborPopulation":"16410","populationCap":"36000","gold":7904455,"goldUpkeep":"0","taxRate":"3","resourceUnixTime":1362399646,"resource1x3600":0,"resource2x3600":3520462185,"resource3x3600":5859908704,"resource4x3600":6337538752,"resource5x3600":0,"resource6x3600":0,"resource7x3600":0,"resource8x3600":0,"resource1Productivity":56200,"resource2Productivity":36100,"resource3Productivity":36100,"resource4Productivity":36100,"resource5Productivity":0,"resource6Productivity":0,"resource7Productivity":0,"resource8Productivity":0,"resource1Capx3600":"20232000000","resource2Capx3600":"12996000000","resource3Capx3600":"12996000000","resource4Capx3600":"12996000000","resource5Capx3600":"36000000","resource6Capx3600":"36000000","resource7Capx3600":"36000000","resource8Capx3600":"36000000","resource1Upkeep":10660016,"resource2Upkeep":"0","resource3Upkeep":"0","resource4Upkeep":"0","resource5Upkeep":"0","resource6Upkeep":"0","resource7Upkeep":"0","resource8Upkeep":"0"},"gather":{"1":{"resourcex3600":"0","resourceRate":"0","lastObservedTS":1362399646,"isCollecting":"1"},"2":{"resourcex3600":"0","resourceRate":"0","lastObservedTS":1362399646,"isCollecting":"1"},"3":{"resourcex3600":"0","resourceRate":"0","lastObservedTS":1362399646,"isCollecting":"1"},"4":{"resourcex3600":"0","resourceRate":"0","lastObservedTS":1362399646,"isCollecting":"1"},"5":{"resourcex3600":"0","resourceRate":"0","lastObservedTS":1362399646,"isCollecting":"1"},"6":{"resourcex3600":"0","resourceRate":"0","lastObservedTS":1362399646,"isCollecting":"1"},"7":{"resourcex3600":"0","resourceRate":"0","lastObservedTS":1362399646,"isCollecting":"1"},"8":{"resourcex3600":"0","resourceRate":"0","lastObservedTS":1362399646,"isCollecting":"1"}}},"135164":{"production":{"ok":true,"mightInc":0,"reports":[],"paid":false,"fiscalUnixTime":1362399363,"happiness":"97","grievance":"0","population":"34920","laborPopulation":"15010","populationCap":"36000","gold":6823,"goldUpkeep":"0","taxRate":"3","resourceUnixTime":1362399646,"resource1x3600":1462274032,"resource2x3600":6138402338,"resource3x3600":4780359798,"resource4x3600":4691558704,"resource5x3600":0,"resource6x3600":0,"resource7x3600":0,"resource8x3600":0,"resource1Productivity":13600,"resource2Productivity":36400,"resource3Productivity":49100,"resource4Productivity":51400,"resource5Productivity":0,"resource6Productivity":0,"resource7Productivity":0,"resource8Productivity":0,"resource1Capx3600":"4896000000","resource2Capx3600":"13104000000","resource3Capx3600":"17676000000","resource4Capx3600":"18504000000","resource5Capx3600":"36000000","resource6Capx3600":"36000000","resource7Capx3600":"36000000","resource8Capx3600":"36000000","resource1Upkeep":88376,"resource2Upkeep":"0","resource3Upkeep":"0","resource4Upkeep":"0","resource5Upkeep":"0","resource6Upkeep":"0","resource7Upkeep":"0","resource8Upkeep":"0"},"gather":{"1":{"resourcex3600":"0","resourceRate":"0","lastObservedTS":1362399646,"isCollecting":"1"},"2":{"resourcex3600":"0","resourceRate":"0","lastObservedTS":1362399646,"isCollecting":"1"},"3":{"resourcex3600":"0","resourceRate":"0","lastObservedTS":1362399646,"isCollecting":"1"},"4":{"resourcex3600":"0","resourceRate":"0","lastObservedTS":1362399646,"isCollecting":"1"},"5":{"resourcex3600":"0","resourceRate":"0","lastObservedTS":1362399646,"isCollecting":"1"},"6":{"resourcex3600":"0","resourceRate":"0","lastObservedTS":1362399646,"isCollecting":"1"},"7":{"resourcex3600":"0","resourceRate":"0","lastObservedTS":1362399646,"isCollecting":"1"},"8":{"resourcex3600":"0","resourceRate":"0","lastObservedTS":1362399646,"isCollecting":"1"}}}},"xp":{"xp":"848214","lvl":53,"progress":48,"curlvlxp":"828388","nextlvlxp":869387}},"upgrade_flag":0,"xp":{"xp":"848214","lvl":53,"progress":48,"curlvlxp":"828388","nextlvlxp":869387},"chatSales":{"s252":{"worldId":"1","saleId":"252","imgFile":"swords","title":"Declaring a Middle-earth Troop Kill Tournament! Ready your armies!","detail":"A Middle-earth Troop Kill Tournament has been declared in your World! Attack your enemies and defend against their armies. We will reward the players who kill the most Might! Tap here for details.","destination":"url:http://i.kabam.com/Wx7Yg2?userId=1911696&server=1&platformid=201","rollSeconds":"30","sort":"1","status":"1","urgent":"0"},"s253":{"worldId":"1","saleId":"253","imgFile":"chest","title":"Oakenshield's Order is in the Shop! Chance to win 10k Troops","detail":"Oakenshield's Order is in the Shop for a LIMITED TIME. Each Box GUARANTEES Tier 2 or 3 TROOPS & a chance to win 10000 MORE! Tap here to visit the Shop.","destination":"shop","rollSeconds":"30","sort":"1","status":"1","urgent":"1"}},"self":{"allMailCount":"527","allReportCount":9620,"allianceDiplomacies":{"friendly":{"a986":{"allianceId":"986","founderUserId":"40568","allianceName":"Blood Brothers","relation":"1","membersCount":"93","rank":46,"might":"99351735","founderUserName":"Mully"},"a435":{"allianceId":"435","founderUserId":"4005","allianceName":"Canadian Shire","relation":"1","membersCount":"51","rank":66,"might":"68374457","founderUserName":"DARKWINGDUCK"},"a1500":{"allianceId":"1500","founderUserId":"68190","allianceName":"Catalunya","relation":"1","membersCount":"40","rank":68,"might":"66649845","founderUserName":"Drac"},"a2479":{"allianceId":"2479","founderUserId":"54943","allianceName":"Creatures","relation":"1","membersCount":"61","rank":26,"might":"187279533","founderUserName":"Your_Dawg"},"a103":{"allianceId":"103","founderUserId":"901","allianceName":"Dark Riders","relation":"1","membersCount":"20","rank":104,"might":"18322598","founderUserName":"Tathar"},"a343":{"allianceId":"343","founderUserId":"4158","allianceName":"Dwarf Warriors","relation":"1","membersCount":"78","rank":18,"might":"219233285","founderUserName":"GandoIf"},"a802":{"allianceId":"802","founderUserId":"25656","allianceName":"Fetch you a Box","relation":"1","membersCount":"28","rank":130,"might":"10007676","founderUserName":"pink"},"a930":{"allianceId":"930","founderUserId":"27836","allianceName":"Ghost Dragons","relation":"1","membersCount":"77","rank":41,"might":"124066896","founderUserName":"Thor512"},"a13441":{"allianceId":"13441","founderUserId":"211592","allianceName":"Grendels Brood","relation":"1","membersCount":"19","rank":null,"might":null,"founderUserName":"zoven77"},"a1989":{"allianceId":"1989","founderUserId":"108276","allianceName":"Imperium","relation":"1","membersCount":"88","rank":57,"might":"78055513","founderUserName":"Apocalypse"},"a7856":{"allianceId":"7856","founderUserId":"279117","allianceName":"Inactive Farm","relation":"1","membersCount":"1","rank":2523,"might":"5525","founderUserName":"YY_FAKIE"},"a10503":{"allianceId":"10503","founderUserId":"47387","allianceName":"Just Me","relation":"1","membersCount":"1","rank":5559,"might":"0","founderUserName":"Smudge_KOR"},"a9340":{"allianceId":"9340","founderUserId":"1544227","allianceName":"Legion of Elves","relation":"1","membersCount":"1","rank":6070,"might":"0","founderUserName":"bigfoot"},"a68":{"allianceId":"68","founderUserId":"639","allianceName":"Lords of Endore","relation":"1","membersCount":"52","rank":22,"might":"198462757","founderUserName":"Adamas"},"a11727":{"allianceId":"11727","founderUserId":"1829088","allianceName":"Magical elves","relation":"1","membersCount":"2","rank":2192,"might":"9303","founderUserName":"BillyBaggins"},"a12115":{"allianceId":"12115","founderUserId":"4178975","allianceName":"MetaI Men","relation":"1","membersCount":"39","rank":95,"might":"22567541","founderUserName":"PrincessB"},"a5737":{"allianceId":"5737","founderUserId":"123097","allianceName":"Northern Empire","relation":"1","membersCount":"85","rank":29,"might":"149634616","founderUserName":"Eylanin"},"a1865":{"allianceId":"1865","founderUserId":"21002","allianceName":"Pyro Hobbits","relation":"1","membersCount":"86","rank":99,"might":"21024403","founderUserName":"Pimp"},"a3632":{"allianceId":"3632","founderUserId":"186770","allianceName":"rehelm pact","relation":"1","membersCount":"3","rank":564,"might":"487598","founderUserName":"barlinthewise"},"a1185":{"allianceId":"1185","founderUserId":"57907","allianceName":"RidersoftheMark","relation":"1","membersCount":"89","rank":73,"might":"55598623","founderUserName":"Origen"},"a934":{"allianceId":"934","founderUserId":"1989","allianceName":"Second age","relation":"1","membersCount":"37","rank":189,"might":"4919272","founderUserName":"StonedOne"},"a7964":{"allianceId":"7964","founderUserId":"81193","allianceName":"Shadowstone","relation":"1","membersCount":"48","rank":24,"might":"190596080","founderUserName":"_Methuselah_"},"a7881":{"allianceId":"7881","founderUserId":"1586168","allianceName":"Strongbrethren","relation":"1","membersCount":"24","rank":156,"might":"7102174","founderUserName":"Yenksilver"},"a7132":{"allianceId":"7132","founderUserId":"264572","allianceName":"The Badgers","relation":"1","membersCount":"3","rank":1128,"might":"105484","founderUserName":"TheHoneyBadger"},"a1111":{"allianceId":"1111","founderUserId":"6023","allianceName":"The Watch","relation":"1","membersCount":"14","rank":460,"might":"766228","founderUserName":"xMcROYALx"},"a3629":{"allianceId":"3629","founderUserId":"135630","allianceName":"THUNDERSTRUCK","relation":"1","membersCount":"82","rank":13,"might":"269682103","founderUserName":"SanAngelo"},"a25":{"allianceId":"25","founderUserId":"153","allianceName":"TombStone","relation":"1","membersCount":"5","rank":486,"might":"669475","founderUserName":"LordWainwright"},"a10494":{"allianceId":"10494","founderUserId":"596234","allianceName":"UrFkd","relation":"1","membersCount":"1","rank":6426,"might":"0","founderUserName":"UrSCR3W3D"},"a7154":{"allianceId":"7154","founderUserId":"29944","allianceName":"Whiskers","relation":"1","membersCount":"47","rank":74,"might":"55386346","founderUserName":"Cason"}},"hostile":{"a12736":{"allianceId":"12736","founderUserId":"3286599","allianceName":"FoxFox","relation":"2","membersCount":"1","rank":2004,"might":"14321","founderUserName":"FoxFox"},"a995":{"allianceId":"995","founderUserId":"30292","allianceName":"HelemansArmy","relation":"2","membersCount":"20","rank":164,"might":"6215007","founderUserName":"Rivendale1920"},"a9809":{"allianceId":"9809","founderUserId":"1541","allianceName":"InsidiousUnited","relation":"2","membersCount":"60","rank":19,"might":"215348936","founderUserName":"phrenikos"},"a8049":{"allianceId":"8049","founderUserId":"107852","allianceName":"RivendalleElves","relation":"2","membersCount":"8","rank":1358,"might":"62353","founderUserName":"Zanebob"},"a8953":{"allianceId":"8953","founderUserId":"19422","allianceName":"The Hated","relation":"2","membersCount":"1","rank":1428,"might":"52618","founderUserName":"DarkHunters"},"a9176":{"allianceId":"9176","founderUserId":"147898","allianceName":"Whippity whip","relation":"2","membersCount":"1","rank":1673,"might":"29778","founderUserName":"Vipertown"}},"friendlyToThem":{"a325":{"allianceId":"325","founderUserId":"4831","allianceName":"THE WARRIORS","relation":"1","membersCount":"1","rank":4489,"might":"389","founderUserName":"Warriorpower"}},"friendlyToYou":{"a9758":{"allianceId":"9758","founderUserId":"1763591","allianceName":"AldmeriDominion","relation":"1","membersCount":"4","might":1125,"founderUserName":"TheWarden"},"a7264":{"allianceId":"7264","founderUserId":"279148","allianceName":"AllianceOfBruce","relation":"1","membersCount":"1","might":2483,"founderUserName":"Kirton"},"a1005":{"allianceId":"1005","founderUserId":"45475","allianceName":"DeathRow","relation":"1","membersCount":"25","might":115,"founderUserName":"RogueAura"},"a10683":{"allianceId":"10683","founderUserId":"2469984","allianceName":"Ghost Army","relation":"1","membersCount":"13","might":479,"founderUserName":"hobo5677"},"a9038":{"allianceId":"9038","founderUserId":"27402","allianceName":"MAGNUS","relation":"1","membersCount":"11","might":283,"founderUserName":"Holty93"},"a8345":{"allianceId":"8345","founderUserId":"421","allianceName":"TheNightsWatch","relation":"1","membersCount":"58","might":80,"founderUserName":"Kellen"}},"allianceId":"1018","allianceName":"Comrade in arms"},"artifactSets":{"inventory":[]},"artifacts":{"20221":"0","20323":"0","20415":"0"},"blueLight":{"max":1600,"cur":746,"level":5},"broadcast":"0","buyUpgradeRate":"0.00022","chatSales":{"s252":{"worldId":"1","saleId":"252","imgFile":"swords","title":"Declaring a Middle-earth Troop Kill Tournament! Ready your armies!","detail":"A Middle-earth Troop Kill Tournament has been declared in your World! Attack your enemies and defend against their armies. We will reward the players who kill the most Might! Tap here for details.","destination":"url:http://i.kabam.com/Wx7Yg2?userId=1911696&server=1&platformid=201","rollSeconds":"30","sort":"1","status":"1","urgent":"0"},"s253":{"worldId":"1","saleId":"253","imgFile":"chest","title":"Oakenshield's Order is in the Shop! Chance to win 10k Troops","detail":"Oakenshield's Order is in the Shop for a LIMITED TIME. Each Box GUARANTEES Tier 2 or 3 TROOPS & a chance to win 10000 MORE! Tap here to visit the Shop.","destination":"shop","rollSeconds":"30","sort":"1","status":"1","urgent":"1"}},"city_unit_count":{"c126934":{"u1":0,"u2":"6996","u4":"553218","u5":"548438","u6":"601364","u7":"123312","u8":"112839","u9":0,"u10":"28100","u11":"83345","u12":"25450","u13":"23700","u14":0,"u15":0,"u16":0},"c135164":{"u1":0,"u2":"3647","u4":"500","u5":0,"u6":"500","u7":0,"u8":0,"u9":0,"u10":0,"u11":"500","u12":"2700","u13":"500","u14":0,"u15":0,"u16":0}},"config":{"allianceHelp":true},"cur_time":"2013-03-04 12:20:46","dataVersion":"1","fortifications":{"city126934":{"fort52":"0","fort53":"0","fort54":"0","fort55":"0","fort56":"0","fort57":"0","fort58":"0","fort59":"0","fort60":"0"},"city135164":{"fort52":"0","fort53":"2","fort54":"2","fort55":"2","fort56":"2","fort57":"0","fort58":"0","fort59":"0","fort60":"0"}},"foundArtifacts":{"126934":false,"135164":false},"hasNewReceiveMail":false,"hasNewReport":false,"hasNewSentMail":false,"hasNewSysMail":false,"newAllInboxCount":null,"newDisasterReportCount":"0","newMailCount":"0","newReportCount":0,"newSentMailCount":0,"newTradeReports":0,"newitems":{"i1":"108","i2":"116","i3":"47","i4":"11","i5":"5","i9":"8","i69":"2","i101":"4","i102":"4","i111":"8","i112":"2","i121":"14","i131":"10","i141":"10","i142":"2","i261":"14","i262":"7","i271":"19","i272":"5","i355":"4","i361":"21","i362":"19","i363":"20","i401":"8","i599":"82","i901":"1","i911":"10","i922":"1","i923":"6","i1001":"11","i1002":"3","i1003":"4","i1004":"5","i1005":"14","i1011":"8","i1012":"6","i1013":"4","i1014":"14","i1015":"29","i1016":"1","i1021":"3","i1022":"2","i1023":"3","i1024":"6","i1025":"15","i1031":"2","i1032":"2","i1033":"3","i1034":"5","i1035":"12","i1041":"2","i1042":"2","i1043":"2","i1044":"13","i1045":"20","i1047":"2","i1202":"1","i10009":"2","i10020":"1","i10030":"1","i10031":"1","i10032":"1","i10033":"1","i10034":"1","i20221":"4","i20323":"4","i20415":"23","i50020":"2","i50050":"1","i50060":"3","i50062":"5","i60001":"2","i60010":"1","i60017":"15","i60018":"1","i60019":"4","i60023":"1","i60024":"1","i60031":"2","i60033":"1","i60035":"3","i60039":"4","i60041":"1","i60044":"6","i60048":"2","i60050":"10"},"ok":true,"player":{"datejoinUnixTime":"1355071835","truceExpireUnixTime":"0","beginproExpireUnixTime":"1355676635","fteFinishUnixTime":"1355098713","userId":"1911696","displayName":"Leith","email":"","fbuid":"0","mobileid":"b1d5ae74028aa35fb1988d3748d69f3d","playerSex":"M","usertype":"201","race":"2","status":"1","dateJoined":"2012-12-09 16:50:35","lastLogin":"2013-03-04 12:11:32","fte_finish_time":"2012-12-10 00:18:33","warStatus":"1","allianceId":"1018","might":13866984,"xp":"847290","title":"53","truceExpireTimestamp":"0000-00-00 00:00:00","beginproExpireTimestamp":"2012-12-16 16:50:35","fogExpireTimestamp":"0000-00-00 00:00:00","cnt_newmsg":"0","cnt_friendreq":"0","cnt_logins":"0","cnt_passreset":"0","cnt_connections":"0","avatarId":"0","photo_host":"0","photo_dir":"0","photo_subdir":"0","photo_name":"0","playerCityLock":"0","officerType":"3"},"players":[],"queue_atkinc":[],"reqmicrotime":1362399646.6834,"resmicrotime":1362399646.7933,"runtime":0.11420297622681,"serverSetting":{"allowJumpAllianceFromInvitation":0},"shopUpgraded":false,"strVersion":"1","timezone":"UTC","updateMarch":[],"updateMight":13866984,"updateSeed":{"ok":false,"city":{"126934":{"production":{"ok":true,"mightInc":0,"reports":[],"paid":false,"fiscalUnixTime":1362399303,"happiness":"97","grievance":"0","population":"34920","laborPopulation":"16410","populationCap":"36000","gold":7904455,"goldUpkeep":"0","taxRate":"3","resourceUnixTime":1362399646,"resource1x3600":0,"resource2x3600":3520462185,"resource3x3600":5859908704,"resource4x3600":6337538752,"resource5x3600":0,"resource6x3600":0,"resource7x3600":0,"resource8x3600":0,"resource1Productivity":56200,"resource2Productivity":36100,"resource3Productivity":36100,"resource4Productivity":36100,"resource5Productivity":0,"resource6Productivity":0,"resource7Productivity":0,"resource8Productivity":0,"resource1Capx3600":"20232000000","resource2Capx3600":"12996000000","resource3Capx3600":"12996000000","resource4Capx3600":"12996000000","resource5Capx3600":"36000000","resource6Capx3600":"36000000","resource7Capx3600":"36000000","resource8Capx3600":"36000000","resource1Upkeep":10660016,"resource2Upkeep":"0","resource3Upkeep":"0","resource4Upkeep":"0","resource5Upkeep":"0","resource6Upkeep":"0","resource7Upkeep":"0","resource8Upkeep":"0"},"gather":{"1":{"resourcex3600":"0","resourceRate":"0","lastObservedTS":1362399646,"isCollecting":"1"},"2":{"resourcex3600":"0","resourceRate":"0","lastObservedTS":1362399646,"isCollecting":"1"},"3":{"resourcex3600":"0","resourceRate":"0","lastObservedTS":1362399646,"isCollecting":"1"},"4":{"resourcex3600":"0","resourceRate":"0","lastObservedTS":1362399646,"isCollecting":"1"},"5":{"resourcex3600":"0","resourceRate":"0","lastObservedTS":1362399646,"isCollecting":"1"},"6":{"resourcex3600":"0","resourceRate":"0","lastObservedTS":1362399646,"isCollecting":"1"},"7":{"resourcex3600":"0","resourceRate":"0","lastObservedTS":1362399646,"isCollecting":"1"},"8":{"resourcex3600":"0","resourceRate":"0","lastObservedTS":1362399646,"isCollecting":"1"}}},"135164":{"production":{"ok":true,"mightInc":0,"reports":[],"paid":false,"fiscalUnixTime":1362399363,"happiness":"97","grievance":"0","population":"34920","laborPopulation":"15010","populationCap":"36000","gold":6823,"goldUpkeep":"0","taxRate":"3","resourceUnixTime":1362399646,"resource1x3600":1462274032,"resource2x3600":6138402338,"resource3x3600":4780359798,"resource4x3600":4691558704,"resource5x3600":0,"resource6x3600":0,"resource7x3600":0,"resource8x3600":0,"resource1Productivity":13600,"resource2Productivity":36400,"resource3Productivity":49100,"resource4Productivity":51400,"resource5Productivity":0,"resource6Productivity":0,"resource7Productivity":0,"resource8Productivity":0,"resource1Capx3600":"4896000000","resource2Capx3600":"13104000000","resource3Capx3600":"17676000000","resource4Capx3600":"18504000000","resource5Capx3600":"36000000","resource6Capx3600":"36000000","resource7Capx3600":"36000000","resource8Capx3600":"36000000","resource1Upkeep":88376,"resource2Upkeep":"0","resource3Upkeep":"0","resource4Upkeep":"0","resource5Upkeep":"0","resource6Upkeep":"0","resource7Upkeep":"0","resource8Upkeep":"0"},"gather":{"1":{"resourcex3600":"0","resourceRate":"0","lastObservedTS":1362399646,"isCollecting":"1"},"2":{"resourcex3600":"0","resourceRate":"0","lastObservedTS":1362399646,"isCollecting":"1"},"3":{"resourcex3600":"0","resourceRate":"0","lastObservedTS":1362399646,"isCollecting":"1"},"4":{"resourcex3600":"0","resourceRate":"0","lastObservedTS":1362399646,"isCollecting":"1"},"5":{"resourcex3600":"0","resourceRate":"0","lastObservedTS":1362399646,"isCollecting":"1"},"6":{"resourcex3600":"0","resourceRate":"0","lastObservedTS":1362399646,"isCollecting":"1"},"7":{"resourcex3600":"0","resourceRate":"0","lastObservedTS":1362399646,"isCollecting":"1"},"8":{"resourcex3600":"0","resourceRate":"0","lastObservedTS":1362399646,"isCollecting":"1"}}}},"xp":{"xp":"848214","lvl":53,"progress":48,"curlvlxp":"828388","nextlvlxp":869387}},"upgrade_flag":0,"xp":{"xp":"848214","lvl":53,"progress":48,"curlvlxp":"828388","nextlvlxp":869387}}}